Workbook

Sheet Affinity
A1: Table 1
A2: Affinity | B2: Key strength
A3: Divine | B3: High defense, Anti-Chaos bonus
A4: Chaos | B4: High cost, powerful units
A5: Arcane | B5: Spending a lot of Crystal to maximize power in short time. A glass cannon.
A6: Nature | B6: Balanced, Union heavy
A7: Bio | B7: Few unit, mutate to other or attack a lot of times, Tech heavy
A8: Cosmic | B8: High discovery capacity, Tech heavy
A9: Anima | B9: Low cost, swarming

Sheet Unit
A1: Table 1
A2: Card Name | B2: Card Type | C2: Cost | D2: ATK | E2: DEF | F2: Affinity | G2: Rarity | H2: Ability | I2: Comment | J2: Formula | K2: Have illustration | L2: Suggested cost | M2: Demo | N2: Test 1 | O2: ="Booster Pack - Blightsilver / "&COUNTIF(N3:N568,"Yes") | P2: ="Booster Pack - Unseen Presence / "&COUNTIF(O3:O568,"Yes") | Q2: ="Booster Pack - Wind of Dominance / "&COUNTIF(P3:P568,"Yes")
A3: Pyromancer | B3: Unit | C3: 900 | D3: 80 | E3: 0 | F3: Arcane | G3: 4 | H3: +30 ATK vs Nature | I3: dropped redundant Affinity | K3: Yes | L3: =(D3*6)+(E3*4) | M3: Yes | Q3: Yes
A4: Angel Gatekeeper | B4: Unit | C4: 1000 | D4: 40 | E4: 90 | F4: Divine | G4: 4 | H4: +50 ATK vs Chaos | I4: dropped redundant Affinity | K4: Yes | L4: =(D4*6)+(E4*4) | M4: Yes | O4: Yes | Q4: Yes
A5: Wandering Swordsman | B5: Unit | C5: 600 | D5: 60 | E5: 60 | F5: Anima | G5: 3 | H5: None | K5: Yes | L5: =(D5*6)+(E5*4) | M5: Yes | O5: Yes | Q5: Yes
A6: Huntress of Green Glade | B6: Unit | C6: 800 | D6: 50 | E6: 50 | F6: Anima | G6: 3 | H6: Immune to 0-cost traps | I6: wording polish | K6: Yes | L6: =(D6*6)+(E6*4) | M6: Yes | O6: Yes
A7: Fierce Gladiator | B7: Unit | C7: 1000 | D7: 70 | E7: 90 | F7: Anima | G7: 3 | H7: +500 Crystal on successful defend | K7: Yes | L7: =(D7*6)+(E7*4)
A8: Canyon Warg | B8: Unit | C8: 750 | D8: 70 | E8: 30 | F8: Nature | G8: 3 | H8: None | K8: Yes | L8: =(D8*6)+(E8*4) | M8: Yes | Q8: Yes
A9: Armored Bee | B9: Unit | C9: 480 | D9: 30 | E9: 0 | F9: Nature | G9: 2 | H9: +60 DEF until the end of that turn once | K9: Yes | L9: =(D9*6)+(E9*4) | M9: Yes | O9: Yes
A10: Armored Rhino | B10: Unit | C10: 720 | D10: 60 | E10: 85 | F10: Nature | G10: 3 | H10: None | K10: Yes | L10: =(D10*6)+(E10*4) | M10: Yes | P10: Yes
A11: Lightbringer | B11: Unit | C11: 1200 | D11: 80 | E11: 40 | F11: Divine | G11: 3 | H11: +100 DEF vs Chaos | I11: dropped redundant Affinity | K11: Yes | L11: =(D11*6)+(E11*4)
A12: Chaotic Wisp | B12: Unit | C12: 100 | D12: 20 | E12: 0 | F12: Chaos | G12: 1 | H12: None | K12: Yes | L12: =(D12*6)+(E12*4) | M12: Yes | O12: Yes
A13: Foul Wisp | B13: Unit | C13: 100 | D13: 0 | E13: 25 | F13: Chaos | G13: 1 | H13: None | K13: Yes | L13: =(D13*6)+(E13*4) | M13: Yes | O13: Yes
A14: Doom Wisp | B14: Unit | C14: 100 | D14: 15 | E14: 15 | F14: Chaos | G14: 1 | H14: None | K14: Yes | L14: =(D14*6)+(E14*4) | M14: Yes | O14: Yes
A15: Night Whisperer | B15: Unit | C15: 900 | D15: 30 | E15: 30 | F15: Chaos | G15: 3 | H15: +30 ATK and DEF for each exposed ‘wisp’ card on its side | I15: ATK&DEF→ATK and DEF | K15: Yes | L15: =(D15*6)+(E15*4) | M15: Yes | P15: Yes
A16: Leorudus the Warlord | B16: Unit | C16: 1150 | D16: 80 | E16: 80 | F16: Anima | G16: 5 | H16: +20 ATK and DEF for each other exposed Anima card on its side | I16: ATK&DEF→ATK and DEF | K16: Yes | L16: =(D16*6)+(E16*4) | M16: Yes | P16: Yes
A17: Aether Warden | B17: Unit | C17: 800 | D17: 30 | E17: 110 | F17: Divine | G17: 3 | H17: In Reckoning if it defends, attacker loses 300 Crystals | K17: Yes | L17: =(D17*6)+(E17*4)
A18: Void Stalker | B18: Unit | C18: 720 | D18: 65 | E18: 25 | F18: Chaos | G18: 3 | H18: +20 ATK if it attack an Exposed unit. | I18: wording polish | K18: Yes | L18: =(D18*6)+(E18*4) | M18: Yes | O18: Yes
A19: Swarmcaller | B19: Unit | C19: 950 | D19: 45 | E19: 45 | F19: Nature | G19: 4 | H19: +15 ATK and DEF for each other exposed Nature card on its side | I19: ATK&DEF→ATK and DEF | K19: Yes | L19: =(D19*6)+(E19*4) | M19: Yes | O19: Yes
A20: Ironclad Sentinel | B20: Unit | C20: 1100 | D20: 55 | E20: 95 | F20: Anima | G20: 5 | H20: Immune to 0-cost traps. Immune to Tech. | I20: Shortened immunity wording. | K20: Yes | L20: =(D20*6)+(E20*4)
A21: Tomb Bandit | B21: Unit | C21: 1000 | D21: 75 | E21: 60 | F21: Anima | G21: 4 | H21: Immune to traps. | I21: Shortened immunity wording. | K21: Yes | L21: =(D21*6)+(E21*4) | M21: Yes | Q21: Yes
A22: Scout Probe | B22: Unit | C22: 700 | D22: 40 | E22: 50 | F22: Cosmic | G22: 3 | H22: Choose and reveal any adjacent cell after it attacked. | I22: square→cell | K22: Yes | L22: =(D22*6)+(E22*4) | M22: Yes | O22: Yes | Q22: Yes
A23: Lab Zombie | B23: Unit | C23: 700 | D23: 55 | E23: 20 | F23: Bio | G23: 3 | H23: With Mutagen flag: +45 ATK vs Nature or Anima. | I23: wording polish | K23: Yes | L23: =(D23*6)+(E23*4) | M23: Yes | P23: Yes
A24: Lab Bloater | B24: Unit | C24: 800 | D24: 20 | E24: 85 | F24: Bio | G24: 4 | H24: With Mutagen flag: owner can destroy both units in Reckoning. Both players pay no Crystal cost. | I24: wording polish | K24: Yes | L24: =(D24*6)+(E24*4) | M24: Yes | P24: Yes | Q24: Yes
A25: Lab Crawler | B25: Unit | C25: 1200 | D25: 95 | E25: 60 | F25: Bio | G25: 5 | H25: With Mutagen flag: this card can target 3 cards | I25: wording polish | K25: Yes | L25: =(D25*6)+(E25*4) | M25: Yes | O25: Yes
A26: Pit Lord | B26: Unit | C26: 1250 | D26: 120 | E26: 100 | F26: Chaos | G26: 5 | H26: Destroy this card after Reckoning with Divine Unit. After this card attacked, halve its ATK and DEF permanently | I26: ATK&DEF→ATK and DEF | K26: Yes | L26: =(D26*6)+(E26*4) | M26: Yes | P26: Yes
A27: Ancient Lich | B27: Unit | C27: 750 | D27: 60 | E27: 60 | F27: Chaos | G27: 3 | H27: Immune to Tech. | I27: Shortened immunity wording. | K27: Yes | L27: =(D27*6)+(E27*4)
A28: Hyperspeed Saucer | B28: Unit | C28: 850 | D28: 80 | E28: 40 | F28: Cosmic | G28: 4 | H28: Permanently increase this card's ATK and DEF by 10 at the end of each of their turn | I28: ATK&DEF→ATK and DEF | K28: Yes | L28: =(D28*6)+(E28*4)
A29: Mountain Sage | B29: Unit | C29: 600 | D29: 50 | E29: 30 | F29: Arcane | G29: 3 | H29: Double effect of Tech card applied to this unit | K29: Yes | L29: =(D29*6)+(E29*4)
A30: War Genie | B30: Unit | C30: 1150 | D30: 100 | E30: 80 | F30: Arcane | G30: 4 | H30: -10 ATK permanently after it attacked | K30: Yes | L30: =(D30*6)+(E30*4) | M30: Yes | Q30: Yes
A31: Grand Wizard | B31: Unit | C31: 1100 | D31: 90 | E31: 70 | F31: Arcane | G31: 4 | H31: In Reckoning: flip a coin. Heads: +30 ATK and DEF until this turn’s end | I31: ATK&DEF→ATK and DEF; Head→Heads | K31: Yes | L31: =(D31*6)+(E31*4)
A32: Archbishop | B32: Unit | C32: 1200 | D32: 70 | E32: 90 | F32: Divine | G32: 4 | H32: If this card would be destroyed, the owner can destroy 1 other Divine card on their side instead | K32: Yes | L32: =(D32*6)+(E32*4) | M32: Yes | Q32: Yes
A33: Space Boy | B33: Unit | C33: 800 | D33: 75 | E33: 65 | F33: Cosmic | G33: 3 | H33: None | K33: Yes | L33: =(D33*6)+(E33*4) | M33: Yes | P33: Yes
A34: Slim Gray Trooper | B34: Unit | C34: 750 | D34: 45 | E34: 45 | F34: Cosmic | G34: 2 | H34: +30 ATK and DEF if 10 or more cells on its side is revealed | I34: ATK&DEF→ATK and DEF | K34: Yes | L34: =(D34*6)+(E34*4)
A35: Horn Face | B35: Unit | C35: 1350 | D35: 85 | E35: 60 | F35: Cosmic | G35: 5 | H35: After successfully attack, flip 3 coins. It can attack again equal to number of head. | K35: Yes | L35: =(D35*6)+(E35*4)
A36: Railgun Tank | B36: Unit | C36: 1500 | D36: 150 | E36: 95 | F36: Anima | G36: 5 | H36: After successfully attack, this card cannot attack on the next of their turn. | K36: Yes | L36: =(D36*6)+(E36*4)
A37: Lazy Troll | B37: Unit | C37: 1000 | D37: 120 | E37: 60 | F37: Nature | G37: 5 | H37: If this card performs an attack, flip a coin. Tails: it stops attacking. | I37: Tail→Tails | K37: Yes | L37: =(D37*6)+(E37*4) | M37: Yes | O37: Yes
A38: Leech Man | B38: Unit | C38: 880 | D38: 60 | E38: 40 | F38: Bio | G38: 4 | H38: +10 DEF permanently after it performed attack on unit. Also +10 ATK with mutagen flag | K38: Yes | L38: =(D38*6)+(E38*4) | M38: Yes | P38: Yes
A39: Immortal Vampire | B39: Unit | C39: 1200 | D39: 30 | E39: 80 | F39: Chaos | G39: 4 | H39: +50 ATK for each other exposed Chaos card on its side. In Reckoning with Divine, destroy this card. | K39: Yes | L39: =(D39*6)+(E39*4) | M39: Yes | O39: Yes | P39: Yes
A40: Vampire Servant | B40: Unit | C40: 800 | D40: 20 | E40: 20 | F40: Chaos | G40: 2 | H40: If a 'Vampire' card will be destroyed, destroy this card instead. Usable face-down. | K40: Yes | L40: =(D40*6)+(E40*4) | M40: Yes | P40: Yes
A41: Bat Swarm | B41: Unit | C41: 200 | D41: 15 | E41: 15 | F41: Chaos | G41: 3 | H41: If a Chaos card is being attacked, they can swap this card’s position with that card. Usable face-down. | K41: Yes | L41: =(D41*6)+(E41*4) | M41: Yes | O41: Yes
A42: Poltergeist | B42: Unit | C42: 700 | D42: 0 | E42: 70 | F42: Chaos | G42: 3 | H42: If this card performs an attack, switch this card’s ATK and DEF | I42: ATK&DEF→ATK and DEF | K42: Yes | L42: =(D42*6)+(E42*4) | M42: Yes | O42: Yes
A43: Giant Mosquito | B43: Unit | C43: 800 | D43: 30 | E43: 20 | F43: Nature | G43: 5 | H43: If this card performs an attack, +ATK equal to half of target’s ATK until the end of this turn | K43: Yes | L43: =(D43*6)+(E43*4)
A44: Street Rogue | B44: Unit | C44: 350 | D44: 25 | E44: 20 | F44: Anima | G44: 1 | H44: +20 ATK against Anima card | K44: Yes | L44: =(D44*6)+(E44*4) | M44: Yes | O44: Yes
A45: Big Thug | B45: Unit | C45: 400 | D45: 40 | E45: 35 | F45: Anima | G45: 2 | H45: None | K45: Yes | L45: =(D45*6)+(E45*4) | M45: Yes | O45: Yes
A46: Goblin Poacher | B46: Unit | C46: 250 | D46: 30 | E46: 10 | F46: Nature | G46: 1 | H46: None | K46: Yes | L46: =(D46*6)+(E46*4) | M46: Yes | Q46: Yes
A47: Ectoplasm | B47: Unit | C47: 800 | D47: 20 | E47: 0 | F47: Bio | G47: 5 | H47: After destroyed in Reckoning, revive 1 owned unit (ability becomes None). Repeat the same battle once. | I47: User confirmed repeat same battle once; grammar. | K47: Yes | L47: =(D47*6)+(E47*4)
A48: Death Stag | B48: Unit | C48: 400 | D48: 45 | E48: 40 | F48: Nature | G48: 2 | H48: None | K48: Yes | L48: =(D48*6)+(E48*4)
A49: Champion of the Valley | B49: Unit | C49: 400 | D49: 35 | E49: 45 | F49: Anima | G49: 2 | H49: +10 ATK permanently if it destroyed a unit. This bonus does not exceed 30 | I49: wording polish | K49: Yes | L49: =(D49*6)+(E49*4)
A50: Magenta the Nightbloom | B50: Unit | C50: 300 | D50: 25 | E50: 40 | F50: Chaos | G50: 1 | H50: Half its DEF permanently at the end of that turn | K50: Yes | L50: =(D50*6)+(E50*4) | M50: Yes | O50: Yes
A51: Jirayu the Rebellious Prince | B51: Unit | C51: 600 | D51: 40 | E51: 40 | F51: Anima | G51: 2 | H51: If this card successfully defended, +10 DEF permanently | K51: Yes | L51: =(D51*6)+(E51*4) | M51: Yes | P51: Yes
A52: Ice Mage | B52: Unit | C52: 400 | D52: 50 | E52: 0 | F52: Arcane | G52: 2 | H52: None | K52: Yes | L52: =(D52*6)+(E52*4) | M52: Yes | Q52: Yes
A53: Asteroid Trooper | B53: Unit | C53: 250 | D53: 30 | E53: 10 | F53: Cosmic | G53: 1 | H53: None | K53: Yes | L53: =(D53*6)+(E53*4)
A54: Slim Gray Tank | B54: Unit | C54: 1000 | D54: 20 | E54: 20 | F54: Cosmic | G54: 5 | H54: +10 ATK and DEF per revealed cell on its side | I54: ATK/DEF→ATK and DEF | K54: Yes | L54: =(D54*6)+(E54*4)
A55: Mafia Associates | B55: Unit | C55: 500 | D55: 45 | E55: 40 | F55: Anima | G55: 2 | H55: At the end of the turn that it’s been exposed, its defense becomes 0 | K55: Yes | L55: =(D55*6)+(E55*4) | M55: Yes | Q55: Yes
A56: Silver Dragon | B56: Unit | C56: 1500 | D56: 155 | E56: 95 | F56: Arcane | G56: 5 | H56: Pay 1000 Crystal tax to command this card for attack | K56: Yes | L56: =(D56*6)+(E56*4)
A57: Energy Wisp | B57: Unit | C57: 100 | D57: 20 | E57: 10 | F57: Arcane | G57: 3 | H57: None | K57: Yes | L57: =(D57*6)+(E57*4)
A58: Wood Wisp | B58: Unit | C58: 100 | D58: 10 | E58: 20 | F58: Nature | G58: 3 | H58: None | K58: Yes | L58: =(D58*6)+(E58*4)
A59: Messenger of Fate | B59: Unit | C59: 500 | D59: 45 | E59: 35 | F59: Divine | G59: 2 | H59: In Reckoning: flip a coin. Heads: +20 ATK and DEF. Tails: -20 ATK and DEF | I59: ATK&DEF→ATK and DEF; Head→Heads | K59: Yes | L59: =(D59*6)+(E59*4)
A60: Armored Wolf | B60: Unit | C60: 800 | D60: 40 | E60: 80 | F60: Nature | G60: 3 | H60: Once in Reckoning: owner may grant this unit +50 ATK and -50 DEF permanently. | I60: User confirmed -50 ATK was typo for -50 DEF. | K60: Yes | L60: =(D60*6)+(E60*4)
A61: Berserker of Ice Sea | B61: Unit | C61: 1000 | D61: 105 | E61: 50 | F61: Anima | G61: 3 | H61: Once: at their turn end, -35 ATK | I61: wording polish | K61: Yes | L61: =(D61*6)+(E61*4)
A62: Armored Elephant | B62: Unit | C62: 800 | D62: 20 | E62: 150 | F62: Nature | G62: 5 | H62: -50 DEF for each successful defense | K62: Yes | L62: =(D62*6)+(E62*4)
A63: Battle Penguin | B63: Unit | C63: 300 | D63: 20 | E63: 15 | F63: Nature | G63: 1 | H63: +15 ATK until the end of that turn, once. | L63: =(D63*6)+(E63*4)
A64: Star Crusader | B64: Unit | C64: 250 | D64: 25 | E64: 25 | F64: Divine | G64: 1 | H64: None | L64: =(D64*6)+(E64*4)
A65: Gryphon | B65: Unit | C65: 1150 | D65: 100 | E65: 85 | F65: Nature | G65: 5 | H65: None | K65: Yes | L65: =(D65*6)+(E65*4) | M65: Yes | P65: Yes
A66: Cleaver Saint | B66: Unit | C66: 1200 | D66: 95 | E66: 80 | F66: DIvine | G66: 4 | H66: None | L66: =(D66*6)+(E66*4)
A67: Succubus | B67: Unit | C67: 600 | D67: 10 | E67: 30 | F67: Chaos | G67: 1 | H67: Once: if survived Reckoning: +ATK and DEF equal to half of that foe’s card | I67: ATK&DEF→ATK and DEF | K67: Yes | L67: =(D67*6)+(E67*4) | M67: Yes | P67: Yes
A68: Wide smile lady | B68: Unit | C68: 200 | D68: 25 | E68: 0 | F68: Chaos | G68: 1 | H68: None | L68: =(D68*6)+(E68*4)
A69: Nuki the Tanuki | B69: Unit | C69: 100 | D69: 10 | E69: 10 | F69: Nature | G69: 1 | H69: Before Reckoning, flip a coin. Heads: swap position with any of own unit. Repeat Reckoning. | I69: Head→Heads | K69: Yes | L69: =(D69*6)+(E69*4) | M69: Yes | Q69: Yes
A70: Tiny Pixie | B70: Unit | C70: 100 | D70: 0 | E70: 0 | F70: Divine | G70: 1 | H70: Once: this card is not destroyed | I70: wording polish | K70: Yes | L70: =(D70*6)+(E70*4) | M70: Yes | O70: Yes
A71: Melissa the Healer | B71: Unit | C71: 700 | D71: 0 | E71: 25 | F71: Divine | G71: 1 | H71: If the owner lose 500 or more Crystals, they recover 300 Crystals | K71: Yes | L71: =(D71*6)+(E71*4) | M71: Yes | O71: Yes
A72: Heavy Tome Preacher | B72: Unit | C72: 300 | D72: 25 | E72: 20 | F72: Divine | G72: 1 | H72: None | K72: Yes | L72: =(D72*6)+(E72*4) | M72: Yes | Q72: Yes
A73: Holy Wisp | B73: Unit | C73: 200 | D73: 10 | E73: 20 | F73: Divine | G73: 1 | H73: +10 ATK vs Chaos | L73: =(D73*6)+(E73*4)
A74: Cloud Soldier | B74: Unit | C74: 200 | D74: 20 | E74: 15 | F74: Divine | G74: 1 | H74: None | L74: =(D74*6)+(E74*4)
A75: Sleeping Kirin | B75: Unit | C75: 400 | D75: 0 | E75: 25 | F75: Divine | G75: 1 | H75: +25 ATK permanently | L75: =(D75*6)+(E75*4)
A76: Ponycorn | B76: Unit | C76: 300 | D76: 25 | E76: 20 | F76: Divine | G76: 2 | H76: None | K76: Yes | L76: =(D76*6)+(E76*4) | M76: Yes | O76: Yes
A77: Nunchuck Nun | B77: Unit | C77: 320 | D77: 25 | E77: 15 | F77: Divine | G77: 1 | H77: + 5 ATK and DEF vs Chaos card | I77: ATK&DEF→ATK and DEF | L77: =(D77*6)+(E77*4)
A78: Joan the Faithful Warrior | B78: Unit | C78: 280 | D78: 25 | E78: 5 | F78: Divine | G78: 1 | H78: If at least 1 exposed Divine unit is on the field, this card gain 35 DEF | K78: Yes | L78: =(D78*6)+(E78*4) | M78: Yes | P78: Yes
A79: Choir Lady Alice | B79: Unit | C79: 250 | D79: 20 | E79: 25 | F79: Divine | G79: 1 | H79: None | K79: Yes | L79: =(D79*6)+(E79*4) | M79: Yes | P79: Yes
A80: Choir Lady Anna | B80: Unit | C80: 250 | D80: 20 | E80: 20 | F80: Divine | G80: 1 | H80: None | K80: Yes | L80: =(D80*6)+(E80*4) | M80: Yes | P80: Yes
A81: Choir Lady Abigail | B81: Unit | C81: 250 | D81: 25 | E81: 15 | F81: Divine | G81: 1 | H81: None | K81: Yes | L81: =(D81*6)+(E81*4) | M81: Yes | P81: Yes
A82: Church Guard | B82: Unit | C82: 150 | D82: 0 | E82: 35 | F82: Divine | G82: 1 | H82: None | K82: Yes | L82: =(D82*6)+(E82*4) | M82: Yes | Q82: Yes
A83: Sniping Fairy | B83: Unit | C83: 350 | D83: 40 | E83: 20 | F83: Divine | G83: 2 | H83: After it becomes exposed, -20 ATK at that turn’s end. | K83: Yes | L83: =(D83*6)+(E83*4) | M83: Yes | O83: Yes
A84: Bomber Fairy | B84: Unit | C84: 500 | D84: 30 | E84: 15 | F84: Divine | G84: 2 | H84: Once: after destroyed a unit, this card can attack 1 more time. | I84: wording polish | K84: Yes | L84: =(D84*6)+(E84*4) | M84: Yes | O84: Yes
A85: Totem Granpa | B85: Unit | C85: 420 | D85: 20 | E85: 20 | F85: Divine | G85: 2 | H85: +30 DEF vs Nature | L85: =(D85*6)+(E85*4)
A86: Golden Senju | B86: Unit | C86: 200 | D86: 15 | E86: 0 | F86: Divine | G86: 2 | H86: Once: after attacked a non-unit cell, this card can attack 1 more time. | I86: wording polish | K86: Yes | L86: =(D86*6)+(E86*4) | M86: Yes | P86: Yes
A87: Cruel Angel | B87: Unit | C87: 250 | D87: 20 | E87: 10 | F87: Divine | G87: 1 | H87: Once: destroy Anima card during battle calculation | I87: wording polish | L87: =(D87*6)+(E87*4)
A88: Sandy Sphinx | B88: Unit | C88: 450 | D88: 20 | E88: 20 | F88: Divine | G88: 1 | H88: In Reckoning if it defends, flip a coin. Heads: the attack does nothing. | I88: Head→Heads | L88: =(D88*6)+(E88*4)
A89: Gemmed Sphinx | B89: Unit | C89: 700 | D89: 40 | E89: 40 | F89: Divine | G89: 2 | H89: In Reckoning if it defends, flip a coin. Heads: the attack does nothing. | I89: Head→Heads | L89: =(D89*6)+(E89*4)
A90: Black Anubis | B90: Unit | C90: 1100 | D90: 75 | E90: 90 | F90: Divine | G90: 4 | H90: +5 ATK at their turn end. This bonus does not exceed 25 | L90: =(D90*6)+(E90*4)
A91: Sunrise Lady | B91: Unit | C91: 300 | D91: 20 | E91: 25 | F91: Divine | G91: 1 | H91: If it attacks: +10 ATK,-10 DEF permanently | K91: Yes | L91: =(D91*6)+(E91*4) | M91: Yes | Q91: Yes
A92: Lucky Statue | B92: Unit | C92: 400 | D92: 40 | E92: 30 | F92: Divine | G92: 2 | H92: +20 DEF vs Chaos | L92: =(D92*6)+(E92*4)
A93: Flame Seraph | B93: Unit | C93: 500 | D93: 50 | E93: 10 | F93: Divine | G93: 2 | H93: None | K93: Yes | L93: =(D93*6)+(E93*4) | M93: Yes | P93: Yes
A94: Halo Guardian | B94: Unit | C94: 450 | D94: 35 | E94: 35 | F94: Divine | G94: 2 | H94: +5 ATK and DEF for each exposed Chaos unit on foe’s field | I94: ATK&DEF→ATK and DEF | L94: =(D94*6)+(E94*4)
A95: Benjamin the Holy Craftsman | B95: Unit | C95: 300 | D95: 25 | E95: 30 | F95: Divine | G95: 2 | H95: +10 ATK and DEF to other Divine card on its side | I95: ATK&DEF→ATK and DEF | L95: =(D95*6)+(E95*4)
A96: Raijin | B96: Unit | C96: 550 | D96: 60 | E96: 0 | F96: Divine | G96: 3 | H96: None | K96: Yes | L96: =(D96*6)+(E96*4) | M96: Yes | O96: Yes
A97: Moonrise Gentleman | B97: Unit | C97: 400 | D97: 40 | E97: 30 | F97: Divine | G97: 2 | H97: If it defends: +10 DEF,-10 ATK | K97: Yes | L97: =(D97*6)+(E97*4) | M97: Yes | Q97: Yes
A98: Fujin | B98: Unit | C98: 450 | D98: 35 | E98: 40 | F98: Divine | G98: 2 | H98: None | K98: Yes | L98: =(D98*6)+(E98*4) | M98: Yes | O98: Yes
A99: Hachiman the Battlemaster | B99: Unit | C99: 500 | D99: 65 | E99: 30 | F99: Divine | G99: 3 | H99: -10 ATK permanently at the end of that turn if this card has not performed attack. | L99: =(D99*6)+(E99*4)
A100: Angel Mauler | B100: Unit | C100: 700 | D100: 45 | E100: 40 | F100: Divine | G100: 2 | H100: This card is not destroyed by Chaos cards | L100: =(D100*6)+(E100*4)
...

Sheet Union
A1: Table 1
A2: Card Name | B2: Card Type | C2: Cost | D2: ATK | E2: DEF | F2: Affinity | G2: Rarity | H2: Partial Ability | I2: Full Ability | J2: Comment | K2: Partial Formula | L2: Full Formula | M2: Union Zone | N2: Have illustration | O2: Demo | P2: Test 1
A3: Gryphon Rider | B3: Union | D3: 125 | E3: 90 | F3: Divine | H3: None | I3: None | K3: 1 ??? + 1 ??? + 1000 cost | L3: Gryphon + 1 Divine + 1000 cost | M3: 10000 01000 00100 00010 00001 | N3: Yes | O3: Yes
A4: Seraphim Fistmaster | B4: Union | D4: 120 | E4: 120 | F4: Divine | H4: Double ATK and DEF against ??? Affinity | I4: Double ATK and DEF against Chaos | J4: Partial: ATK&DEF→ATK and DEF; dropped redundant Affinity | Full: ATK&DEF→ATK and DEF | K4: 1 ??? + 1 ??? + 1500 cost | L4: 1 ‘Seraph’ unit + 1 Divine (≥ 800 cost) + 1500 cost | M4: 11011 10001 00000 10001 11011 | N4: Yes | O4: Yes
A5: Gaia Turtle | B5: Union | D5: 0 | E5: 205 | F5: Nature | H5: None | I5: None | K5: 2 ??? + 2000 cost | L5: 2 any units (≥90 DEF) + 2000 cost | M5: 00000 00000 01110 01110 00000 | N5: Yes | O5: Yes
A6: Barros the Colossal | B6: Union | D6: 150 | E6: 130 | F6: Nature | H6: None | I6: None | K6: 2 ???+ 1500 cost | L6: 2 Nature (≥ 800 cost) + 1500 cost | M6: 00000 01010 00100 01010 00000 | N6: Yes | O6: Yes
A7: X-Death Squad | B7: Union | D7: 50 | E7: 50 | F7: Anima | H7: In Reckoning, pay ???, destroy foe’s unit. They pay ???. | I7: In Reckoning: pay 1000, destroy foe’s unit. They pay no Crystal cost. | J7: Full: wording polish | K7: 1 ??? + 2 ??? + 800 cost | L7: 1 Anima (≥ 800 cost) + 2 Anima + 800 cost | M7: 10101 00000 10101 00000 10101 | N7: Yes | O7: Yes
A8: Rocket Marauder | B8: Union | D8: 125 | E8: 105 | F8: Bio | H8: None | I8: None | K8: 1 ??? + 1 ??? + 1000 cost | L8: 1 Bio (≥ 800 cost) + 1 Anima (≥ 800 cost) + 1000 cost | M8: 00000 00000 00000 01010 10101 | N8: Yes | O8: Yes
A9: Lord of Terror | B9: Union | D9: 150 | E9: 100 | F9: Chaos | H9: -50 ATK if ??? | I9: -50 ATK if attacks Dead End | K9: 2 ??? + 1500 cost | L9: 2 Chaos (≥ 800 cost) + 1500 cost | M9: 00000 00100 00100 01110 00100 | N9: Yes | O9: Yes
A10: Armored Dino | B10: Union | D10: 95 | E10: 60 | F10: Nature | H10: In Reckoning, pay ??? Crystal cost to +??DEF | I10: In Reckoning: pay 1000 Crystal cost to +60 DEF | J10: Full: wording polish | K10: 1 ??? + 1 ??? + 700 cost | L10: 1 Armored Nature card + 1 Nature (≥ 700 cost) + 800 cost | M10: 00000 01110 11111 00000 00000 | N10: Yes | O10: Yes
A11: Greater Succubus | B11: Union | D11: 30 | E11: 50 | F11: Chaos | H11: Once, after Reckoning: +ATK and DEF equal to ??? | I11: Once: after Reckoning: +ATK and DEF equal to half of that foe’s card | J11: Partial: ATK&DEF→ATK and DEF | Full: ATK&DEF→ATK and DEF | K11: 1 ??? + 1 ??? + 800 cost | L11: 1 Succubus + 1 Chaos + 800 cost | M11: 00100 11111 10001 00000 00000 | N11: Yes | O11: Yes
A12: Pixie Queen | B12: Union | D12: 30 | E12: 30 | F12: Divine | H12: +5 ATK for each ???? | I12: +5 ATK for each Divine cards on its side | K12: 1 ??? + 1 ??? + 300 cost | L12: 1 Tiny Pixie + 1 Divine+ 300 cost | M12: 00100 00100 10001 10101 01010 | N12: Yes | O12: Yes
A13: Diamond Unicorn | B13: Union | D13: 30 | E13: 35 | F13: Divine | H13: Once Union, ??? until this turn’s end | I13: Once Union, +15 ATK until this turn’s end | K13: 1 ??? + 1 ??? + 500 cost | L13: 1 Ponycorn + 1 Divine card + 500 cost | M13: 00100 01010 10001 01010 00100 | N13: Yes | O13: Yes
A14: Choir Lead Amber | B14: Union | D14: 35 | E14: 35 | F14: Divine | H14: +20 ATK to all ????? | I14: +20 ATK to all Divine units on its side | K14: 3 ??? + 500 cost | L14: 3 Choir Lady cards + 500 cost | M14: 01100 01011 01001 11000 11000 | N14: Yes | O14: Yes
A15: Raijin and Fujin | B15: Union | D15: 80 | E15: 80 | F15: Divine | H15: None | I15: None | K15: 1 ??? + 1 ??? + 800 cost | L15: Raijin + Fujin + 800 cost | M15: 10001 10001 10001 10001 10001 | N15: Yes | O15: Yes
A16: Sky Protector | B16: Union | D16: 0 | E16: 0 | F16: Divine | H16: If this card defends, DEF becomes ???, ATK becomes ???. If this card performs attack, ATK becomes ???, DEF becomes ???. | I16: If this card defends, DEF becomes 60, ATK becomes 0. If this card performs attack, ATK becomes 60, DEF becomes 0. | K16: 1 ??? + 1 ??? + 400 cost | L16: Sunrise Lady + Moonrise Gentleman + 400 cost | M16: 11111 00000 00000 00000 00000 | N16: Yes | O16: Yes
A17: Giant Mining Pod | B17: Union | D17: 20 | E17: 80 | F17: Cosmic | H17: If this card attacks a Dead End, receive ???Crystals | I17: If this card attacks a Dead End, receive 200 Crystals | K17: 1 ??? + 1 ??? + 500 cost | L17: 1 Miner probe + 1 Cosmic + 500 cost | M17: 11111 01110 01110 00100 00000 | N17: Yes | O17: Yes
A18: Kitsune | B18: Union | D18: 35 | E18: 35 | F18: Chaos | H18: None | I18: None | K18: 1 ??? + 1 ??? + 300 cost | L18: Dark Monk + 1 Chaos + 300 cost | M18: 01100 00110 01100 00110 01100 | N18: Yes | O18: Yes
A19: Ten Arms Yaksa | B19: Union | D19: 45 | E19: 30 | F19: Chaos | H19: This card can choose ?? attack targets. -?? ATK for each successful attack. | I19: This card can choose two attack targets. -5 ATK for each successful attack. | K19: 1 ??? + 1 ??? + 600 cost | L19: Yaksa + 1 Chaos + 600 cost | M19: 11011 00100 00100 01110 01010 | N19: Yes | O19: Yes
A20: Skeleton Overlord | B20: Union | D20: 50 | E20: 5 | F20: Chaos | H20: None | I20: None | K20: 3 ??? + 400 cost | L20: 3 Skeleton cards + 400 cost | M20: 01110 00000 11111 00000 01110 | N20: Yes | O20: Yes
A21: Katana Shark | B21: Union | D21: 75 | E21: 50 | F21: Nature | H21: None | I21: None | K21: 3 ??? + 800 cost | L21: 3 ‘Sharks’ name + 800 cost | M21: 11000 00100 00010 00010 00001 | N21: Yes | O21: Yes
A22: Rocket Peacock | B22: Union | D22: 150 | E22: 100 | F22: Nature | H22: After this card battles, select 1 foe’s card, flip a coin. Head: ??? | I22: After this card battles, select 1 foe’s card, flip a coin. Heads: destroy that card | J22: Full: Head→Heads | K22: 1 ??? + 1 ??? + 1500 cost | L22: Ostrich Cannon + 1 Nature + 1500 cost | M22: 10001 10001 10001 00000 00100 | N22: Yes | O22: Yes
A23: Scarlet Shroom | B23: Union | D23: 0 | E23: 80 | F23: Nature | H23: If ???, put venom flag on all ???. | I23: Once Union, put venom flag on all foe’s Exposed unit | J23: Full: wording polish | K23: 2 ??? + 500 cost | L23: 2 Nature cards + 500 cost | M23: 11111 00100 00100 00100 00000 | N23: Yes | O23: Yes
A24: Ancient Lizard | B24: Union | D24: 75 | E24: 75 | F24: Nature | H24: None | I24: None | K24: 1 ??? + 1 ???+ 800 cost | L24: 1 Flame Lizard + 1 Nature + 800 cost | M24: 00000 00100 01110 00100 00000 | N24: Yes | O24: Yes
A25: Burning Phoenix | B25: Union | D25: 125 | E25: 50 | F25: Arcane | H25: Cannot be destroyed by ???. If targeted by tech, ??? | I25: Cannot be destroyed by non-union cards. If targeted by Tech, destroy this card. | J25: Full: wording polish | K25: 1 ??? + 1 ??? + 1 ??? + 800 cost | L25: 1 Arcane (≥ 500 cost) + 1 Nature (≥ 500 cost) + 1 Divine (≥ 500 cost) + 800 cost | M25: 00100 01110 10101 00000 00000 | N25: Yes | O25: Yes
A26: Berserk Hyena | B26: Union | D26: 40 | E26: 0 | F26: Nature | H26: None | I26: None | K26: 2 ???+ 500 cost | L26: 2 Nature + 500 cost | M26: 00000 11111 10101 10101 00000 | N26: Yes | O26: Yes
A27: False Prophet | B27: Union | D27: 20 | E27: 40 | F27: Divine | H27: At their turn’s end: Reveal ???. If it was a Dead End, destroy this card. Otherwise, gain ??? | I27: At their turn’s end: Reveal 1 foe’s cell. If it was a Dead End, destroy this card. Otherwise, gain 600 Crystals. | J27: Full: wording polish | K27: 2 ??? + 300 cost | L27: 2 Divine cards + 300 cost | M27: 00100 01010 00100 00000 00000 | N27: Yes | O27: Yes
A28: Colorful Mage | B28: Union | D28: 40 | E28: 40 | F28: Arcane | H28: Foe’s non-Arcane get ??? in Reckoning with this card | I28: Foe’s non-Arcane get -10 ATK and DEF permanently in Reckoning with this card | J28: Full: ATK&DEF→ATK and DEF | K28: ??? + ???+ ??? + 500 cost | L28: Red Mage + Green Mage + Blue Mage + 500 cost | M28: 00001 00010 01100 01100 10000 | N28: Yes | O28: Yes
A29: Grand Fort Captain | B29: Union | D29: 45 | E29: 40 | F29: Anima | H29: None | I29: None | K29: 2 ??? + 500 cost | L29: 2 Grand Fort card + 500 cost | M29: 00000 00100 01110 00100 00000 | N29: Yes | O29: Yes
A30: Volatile Slasher | B30: Union | D30: 50 | E30: 45 | F30: Bio | H30: Once, after Reckoning with non-Bio, it gain ???. | I30: Once: after Reckoning with non-Bio, it gain +50 ATK permanently. | J30: Full: wording polish | K30: 1 ??? + 1 ??? + 1000 cost | L30: 1 Bladeshifter + 1 Bio card + 1000 cost | M30: 10000 01100 01100 01100 10000 | N30: Yes | O30: Yes
A31: Moon Tribe Shaman | B31: Union | D31: 25 | E31: 55 | F31: Cosmic | H31: Upon union, revive 1 ???. Double its cost. | I31: Upon union, revive 1 Moon non-Union card. Double its cost. | K31: 1 ??? + 1 ??? + 500 cost | L31: 1 Moon card+ 1 Cosmic card + 500 cost | M31: 10001 01010 00100 00100 00100 | N31: Yes | O31: Yes
A32: Rebel King | B32: Union | D32: 60 | E32: 40 | F32: Anima | H32: At the end of foe’s turn: ??? and swap its ATK and DEF | I32: At the end of foe’s turn: the owner of this card select 1 Exposed foe’s unit and swap its ATK and DEF | J32: Partial: ATK&DEF→ATK and DEF | Full: ATK&DEF→ATK and DEF | K32: ??? + ??? + 800 cost | L32: Jirayu the Rebellious Prince + 1 Anima card (≥ 500 cost) + 800 cost | M32: 00100 00000 10101 00100 00100 | N32: Yes | O32: Yes
A33: Kiba the Giant Slayer | B33: Union | D33: 80 | E33: 55 | F33: Anima | H33: +??? vs Union | I33: +30 ATK vs Union | K33: ??? + ??? + 1000 cost | L33: Kiyoko the Death Whisper + Silver Spearman + 1000 cost | M33: 01010 01010 01010 01010 01010 | N33: Yes | O33: Yes
A34: Moon Lady Ninja | B34: Union | D34: 65 | E34: 50 | F34: Anima | H34: Once, this card is ???. | I34: Once: this card is not destroyed. | J34: Full: wording polish | K34: ??? + ??? + 800 cost | L34: Kiyoko the Death Whisper + 1 Anima card + 800 cost | M34: 00100 00100 01110 00100 00100 | N34: Yes | O34: Yes
A35: Imperial Frame | B35: Union | D35: 45 | E35: 30 | F35: Cosmic | H35: None | I35: None | K35: ??? + ??? + 500 cost | L35: Laser Walker + 1 Cosmic card + 500 cost | M35: 00111 00001 10001 10000 11100 | N35: Yes | O35: Yes
A36: Giant Meteor Vergaia | B36: Union | D36: 60 | E36: 0 | F36: Cosmic | H36: Destroy it at turn's end, then destroy all ??? | I36: Destroy it at turn's end, then destroy all Exposed foe’s units surrounding the card that this card attacked. | J36: Full: wording polish | K36: ??? + ??? + 1000 cost | L36: Striker Comet + 2 Cosmic card + 1000 cost | M36: 10000 01000 00000 00111 00111 | N36: Yes | O36: Yes
A37: Blood-hungry Mutant | B37: Union | D37: 55 | E37: 40 | F37: Cosmic | H37: After destroying foe’s card: ??? | I37: After destroying foe’s card: +80 Crystals | K37: 2 ??? + 600 cost | L37: 2 Mutant cards + 600 cost | M37: 00000 01010 10101 01010 00000 | N37: Yes | O37: Yes
A38: Gamma Mermaid | B38: Union | D38: 30 | E38: 20 | F38: Bio | H38: Non-Bio defender get ???. With Mutagen Flag: +20 ??? | I38: Non-Bio defender get -20 DEF. With Mutagen flag: +20 ATK and DEF to all ally Bio units | J38: Full: ATK&DEF→ATK and DEF | K38: ??? + ??? + 1000 cost | L38: 1 Gamma cards + 1 Bio card + 500 cost | M38: 00000 01110 01010 01110 00000 | N38: Yes | O38: Yes
A39: Tendrill Tyrant | B39: Union | D39: 90 | E39: 110 | F39: Bio | H39: Can attack ? times per turn | I39: Can attack 3 times per turn | K39: 1 ??? + 2 ??? + 1500 cost | L39: 1 Bio with mutagen flag + 2 Bio (≥ 800 cost) + 1500 cost | M39: 00100 00100 11111 00100 00100
A40: Helios the Prideful Fortress | B40: Union | D40: 145 | E40: 100 | F40: Cosmic | H40: As long as there is exposed ???, this card cannot be ??? | I40: With another exposed Cosmic: this card cannot be destroyed | K40: 2 ??? + 1500 cost | L40: 2 Cosmic (≥ 800 cost) + 1500 cost | M40: 00100 01010 10001 01010 00100
A41: Slim Gray Plasma Bomber | B41: Union | D41: 80 | E41: 60 | F41: Cosmic | H41: +?? ATK and DEF if ?? or more of cells on its side is revealed | I41: +100 ATK and DEF if 15 or more cells on its side is revealed | J41: Partial: ATK&DEF→ATK and DEF | Full: ATK&DEF→ATK and DEF | K41: 1 ??? + 1 ??? + 1000 cost | L41: 1 Slim Gray + 1 Cosmic (≥ 800 cost) + 1000 cost | M41: 00100 01110 01010 01110 00000
A42: Interplanetary Assassin | B42: Union | D42: 50 | E42: 70 | F42: Cosmic | H42: +?? ATK vs Cosmic | I42: +100 ATK vs Cosmic | K42: 1 ??? + 1 ??? + 1500 cost | L42: 1 Cosmic (≥ 500 cost) + 1 Cosmic + 1500 cost | M42: 00100 11111 00000 11111 00100
A43: Bioterrorist | B43: Union | D43: 150 | E43: 0 | F43: Bio | H43: Destroy this card after ??? | I43: Destroy this card after battle calculation | K43: 2 ??? + 1000 cost | L43: 2 Bio cards (≥ 800 cost) + 1000 cost | M43: 10001 01010 00000 01010 10001
A44: One Winged Angel | B44: Union | D44: 120 | E44: 120 | F44: Divine | H44: +??? ATK permanently at ??? | I44: Once: +30 ATK permanently at the end of their turn | J44: Full: wording polish | K44: 1 ??? + 1 ??? + 1500 cost | L44: 1 Cleaver Saint + 1 Divine card + 1500 cost | M44: 00011 00011 00011 00011 00011
A45: Genesis Mech | B45: Union | D45: 60 | E45: 40 | F45: Divine | H45: Once, destroy ???or ??? card | I45: Once: destroy Divine or Anima card | J45: Full: wording polish | K45: 1 ??? + 1 ??? + 1000 cost | L45: 1 Cruel Angel + 1 Anima Card + 1000 cost | M45: 11111 11111 00000 00000 00000
A46: Keeper of the Afterlife | B46: Union | D46: 40 | E46: 65 | F46: Divine | H46: At battle calculation, flip a coin. If head, ???? | I46: At battle calculation, flip a coin. Heads: the attack does nothing | J46: Full: Head→Heads | K46: 1 ??? + 1 ???+ 1000 cost | L46: 1 Sphinx unit + 1 Divine card + 1000 cost | M46: 00000 00000 00100 01110 11111
A47: Keeper of the Sun | B47: Union | D47: 70 | E47: 35 | F47: Divine | H47: This card cannot attack if there is card with affinity other than ??? Or ??? | I47: This card cannot attack if there is card with affinity other than Divine or Anima on its side | K47: 1 ???+ ??? + 1000 cost | L47: 1 Sphinx unit + 1 Anima + 1000 cost | M47: 11111 01110 00100 00000 00000
A48: Keeper of Righteous | B48: Union | D48: 90 | E48: 80 | F48: Divine | H48: +??? ATK vs ?? and ?? | I48: +20 ATK vs Chaos and Arcane | K48: 2 ???+ 1000 cost | L48: 2 Sphinx units + 1000 cost | M48: 10001 01010 00100 01010 10001
A49: Lucky Wanderer | B49: Union | D49: 70 | E49: 50 | F49: Divine | H49: During the end of that turn, flip a coin. If head, +??? ATK. If tail, +?? DEF | I49: During the end of that turn, flip a coin. Heads: +10 ATK. Tails: +10 DEF | J49: Full: Head→Heads; Tail→Tails | K49: 1 ??? + 1 ??? + 1000 cost | L49: 1 Lucky Statue + 1 Divine card + 1000 cost | M49: 00100 00100 00100 00100 00100
A50: Joyce the Rafflesia | B50: Union | D50: 45 | E50: 45 | F50: Divine | H50: At the end of this turn, +??? ATK and DEF ???? | I50: At the end of this turn, +5 ATK and DEF permanently. | J50: Partial: ATK&DEF→ATK and DEF | Full: ATK&DEF→ATK and DEF | K50: 1 ??? + 1 ??? + 1000 cost | L50: Bloom Fairy + 1 Nature card + 1000 cost | M50: 11111 11011 00100 00100 00100
A51: Twin Axe Saintess | B51: Union | D51: 40 | E51: 30 | F51: Divine | H51: This card can ??? per turn | I51: This card can attack twice per turn | K51: 1??? + 1 ??? + 1000 cost | L51: Lady of the Sacred Pond + 1 Anima + 600 cost | M51: 11011 01010 01010 01010 00000
A52: Blast Beam Seraph | B52: Union | D52: 100 | E52: 50 | F52: Divine | H52: None | I52: None | K52: 1 ??? + 1 ??? + 1000 cost | L52: Gerald of the Heavenly Light + 1 Divine + 1000 cost | M52: 11111 00100 11111 00100 00000
A53: Balthier the Supreme Holiness | B53: Union | D53: 100 | E53: 100 | F53: Divine | H53: +??? ATK and DEF for each ???cards on the field. This bonus does not exceed maximum of 1??? | I53: +50 ATK and DEF for each Divine cards on the field. This bonus does not exceed maximum of 100 | J53: Partial: ATK&DEF→ATK and DEF | Full: ATK&DEF→ATK and DEF | K53: 2 ??? + 1500 cost | L53: 2 Divine (≥800 cost) + 1500 cost | M53: 00100 11111 00100 00100 00100
A54: Oblivion Dragon | B54: Union | D54: 200 | E54: 0 | F54: Chaos | H54: When this card defends, halve its ??? an??? | I54: When this card defends, halve its attack and increase DEF by that amount permanently | J54: Full: wording polish | K54: 4 ??? + 2000 cost | L54: 4 Chaos card (≥500 cost) + 2000 cost | M54: 10001 00000 00000 00000 10001
A55: Mass Extinction Dragon | B55: Union | D55: 250 | E55: 180 | F55: Nature | H55: Summoned: destroy all ??? | I55: Summoned: destroy all other Exposed ally units. no Crystal cost. | J55: Full: wording polish | K55: 5 ??? + 3000 Crystals | L55: 5 Nature cards + 3000 Crystals | M55: 10001 00000 00100 00010 10001
A56: Beowolf | B56: Union | D56: 55 | E56: 50 | F56: Nature | H56: +?? ATK when this card can destroy ??? | I56: +25 ATK when this card can destroy a unit card | K56: 1 ??? + 1 ??? + 1000 cost | L56: 1 Kulu the Alpha Leader + 1 Anima + 1000 cost | M56: 10101 00000 01010 00000 10101
A57: Dew the Heroic Prince | B57: Union | D57: 80 | E57: 70 | F57: Nature | H57: At battle calculation, +?? ATK and +?? DEF vs ??? | I57: At battle calculation, +40 ATK and +40 DEF vs Union cards | K57: 1 ??? + 1 ??? + 1000 cost | L57: 1 Dew the Frog Knight + 1 card including ‘princess’ name or card with princess flag + 1000 cost | M57: 11011 00000 00100 00100 11011
A58: Gemina the Supreme Queen | B58: Union | D58: 90 | E58: 90 | F58: Anima | H58: Both player cannot use ??? while this card is exposed. This card is unaffected by ???. | I58: Both player cannot use Tech while this card is exposed. This card is unaffected by traps. | J58: Full: wording polish | K58: 3 ??? + 1000 cost | L58: 3 ‘Princess’ or card with princess flag + 1000 cost | M58: 01110 10001 10001 10001 01110
A59: Wild Manticore | B59: Union | D59: 50 | E59: 85 | F59: Nature | H59: +?? ATK at the end of their turn. Whenever this card attacks, ?? | I59: +20 ATK at the end of their turn. Reset this bonus after performed attack. | K59: 1 ??? + 1 ??? + 1 ??? + 1000 cost | L59: Wild Centaur + Wild Minotaur + Wild Pegasus + 1000 cost | M59: 00000 01110 01010 01110 00000
A60: Wyriah the Roc | B60: Union | D60: 80 | E60: 25 | F60: Nature | H60: This card is unaffected by ??? | I60: This card is unaffected by trap effect | K60: 1 ??? + 1 ??? + 1000 cost | L60: 1 Steel Eagle + 1 Nature (≥ 800 cost) + 1000 cost | M60: 00000 01110 11111 00100 00100
A61: Mad Eye the Collector | B61: Union | D61: 60 | E61: 60 | F61: Cosmic | H61: In Reckoning, the owner can choose to destroy ??? to +??? ATK and DEF | I61: In Reckoning: the owner can choose to destroy 1 trap card on its side to +60 ATK and DEF | J61: Partial: ATK&DEF→ATK and DEF | Full: ATK&DEF→ATK and DEF | K61: 1 ??? + 1 ??? + 1000 cost | L61: 1 Space Janitor + 1 Cosmic + 1000 cost | M61: 00000 00100 01110 00100 00000
A62: Ice Hawk | B62: Union | D62: 35 | E62: 25 | F62: Nature | H62: Defender is ??? on next foe’s turn. | I62: Defender is unable to attack on next foe’s turn. | K62: 1 ??? + 1 ???+ 1000 cost | L62: Drill Woodpecker + 1 Nature + 1000 cost | M62: 10100 01111 10100 00000 00000
A63: Dwarven Drill | B63: Union | D63: 55 | E63: 80 | F63: Arcane | H63: If this card have not attacked and this turn ends, reveal ??? | I63: If this card have not attacked and this turn ends, reveal 2 card on foe’s side. | K63: 2 ??? + 1000 Crystal. | L63: 2 Dwarven cards + 1000 Crystal. | M63: 00001 01111 11100 00000 00000
A64: Cullan the Flaming Blade | B64: Union | D64: 40 | E64: 30 | F64: Arcane | H64: +??? ATK and DEF vs Nature | I64: +30 ATK and DEF vs Nature | J64: Partial: ATK&DEF→ATK and DEF | Full: ATK&DEF→ATK and DEF | K64: 1 ??? + 1 ??? + 1000 cost | L64: Cullan the Magic Swordsman + Red Mage + 1000 cost | M64: 00001 00010 01100 01110 10000
A65: The Undertaker | B65: Union | D65: 90 | E65: 75 | F65: Chaos | I65: If foe destroys a card on its side, gain +15 ATK permanently (max +60). | L65: Mad Doctor + 1 Chaos card + 1000 cost | M65: 00000 00000 01110 01110 01110
A66: Ethereal Marquees | B66: Union | D66: 175 | E66: 140 | F66: Arcane | H66: -80 DEF if ??? | I66: -80 DEF if defends against Arcane card. If this card battles and survived, pay 500 Crystal cost | L66: Nobleman of Luminaso + 1 Arcane + 1500 cost | M66: 00100 01010 10101 01010 10101
A67: Charm Mistress | B67: Union | D67: 30 | E67: 50 | F67: Arcane | I67: Foe’s turn start: flip a coin. Head, foe can only attack once. | L67: Alluring Spellcaster + 1 Arcane + 1000 cost | M67: 00000 01010 01110 00100 00000
A68: Chronoteleporter | B68: Union | D68: 60 | E68: 80 | F68: Arcane | I68: When ally Arcane unit is targeted, owner can swap its location with this card. | L68: Freya the Rift Walker + Bingo the Chrono Rabbit + 1000 cost. | M68: 00010 01000 00010 01000 00001
A69: Death Colony | B69: Union | D69: 180 | E69: 150 | F69: Bio | I69: This card can only choose attack target in the same pattern as its union zone | L69: Long Tongue + 1 Bio card + 1000 cost. | M69: 10001 01010 00100 01010 10001
A70: Diamond Elemental | B70: Union | D70: 60 | E70: 90 | F70: Arcane | I70: None | L70: Fire Elemental + Earth Elemental + 1000 cost | M70: 01010 01110 01110 00100 00000
A71: Ice Elemental | B71: Union | D71: 70 | E71: 50 | F71: Arcane | I71: Card that battles this card cannot perform attack until the end of their next turn. | L71: Water Elemental + Wind Elemental + 1000 cost | M71: 00000 01110 00100 01110 00000
A72: Cloud Elemental | B72: Union | D72: 60 | E72: 60 | F72: Arcane | I72: Once: this card is not destroyed | J72: Full: wording polish | L72: Fire Elemental + Water Elemental + 1000 cost | M72: 00100 00100 01110 01110 00000
A73: Thunder Elemental | B73: Union | D73: 80 | E73: 55 | F73: Arcane | I73: After successful attack, reveal 1 foe’s card | L73: Fire Elemental + Wind Elemental + 1000 cost | M73: 00010 00110 00100 01100 01000
A74: Wood Elemental | B74: Union | D74: 65 | E74: 70 | F74: Arcane | I74: At the end of this turn, +10 DEF permanently | L74: Water Elemental + Earth Elemental + 1000 cost | M74: 00000 00000 01110 01110 01110
A75: Sand Elemental | B75: Union | D75: 50 | E75: 50 | F75: Arcane | I75: +40 ATK and DEF vs Non-Arcane cards | J75: Full: ATK&DEF→ATK and DEF | L75: Wind Elemental + Earth Elemental + 1000 cost | M75: 00000 01110 01110 01110 00000
A76: Nuclear Elemental | B76: Union | D76: 90 | E76: 80 | F76: Arcane | I76: At the end of this turn, +10 ATK permanently | L76: Mind Elemental + Fire Elemental + 1500 cost | M76: 00000 01110 01110 01110 00000
A77: Acid Elemental | B77: Union | D77: 50 | E77: 100 | F77: Arcane | I77: Summoned : put Acid flag on all of foe’s Exposed unit. Card with Acid flag get -10 DEF at the end of foe’s turn | J77: Full: wording polish | L77: Mind Elemental + Water Elemental + 1500 cost | M77: 00000 01110 01110 01110 00000
A78: Vacuum Elemental | B78: Union | D78: 155 | E78: 0 | F78: Arcane | I78: None | L78: Mind Elemental + Wind Elemental + 1500 cost | M78: 00000 01110 01110 01110 00000
A79: Magnet Elemental | B79: Union | D79: 10 | E79: 120 | F79: Arcane | I79: Foe’s non-Arcane cards cannot target Exposed unit other than this card. | J79: Full: wording polish | L79: Mind Elemental + Earth Elemental + 1500 cost | M79: 00000 01110 01110 01110 00000
A80: Dwarven Berserker | B80: Union | D80: 120 | E80: 0 | F80: Arcane | I80: This card can attack twice | L80: 1 Dwarven card + 1 Arcane or Anima card + 1500 cost | M80: 01110 10101 00100 00100 00000
A81: Tholin Whale
A82: Fujin Raijin Suigin | D82: 160 | E82: 160 | F82: Divine | I82: None | L82: Fujin + Raijin + Suigin + 1000 cost
A83: Dark Invader | F83: Cosmic | L83: Liam the Vastrunner + 1 Cosmic card + 1500 cost
A84: Europan Tankmaster | F84: Cosmic | L84: 2 Europan cards + 1000 cost
A85: Nanomites Dragon | F85: Bio
A86: Capnomancer | B86: Union | C86: 0 | D86: 0 | E86: 120 | F86: Arcane | H86: Their turn start: the owner can destroy this card to ??? | I86: Turn start: owner may destroy this unit to revive Pyromancer. | J86: Full: Single ability only (no coin flip); shortened wording. | K86: 1 ??? | L86: 1 Pyromancer + 1000 cost | M86: 00000 01110 01110 01110 00000
A87: Immortal Siegfried | F87: Anima
A88: Dark Champion | D88: 170 | E88: 150 | H88: Cannot select unit with 0 DEF as attack target. Destroy this card in Reckoning with 0 ATK unit | I88: Cannot select unit with ?? DEF as attack target. Destroy this card in Reckoning with ???

Sheet Trap
A1: Table 1
A2: Card Name | B2: Card Type | C2: Cost | D2: ATK | E2: DEF | F2: Affinity | G2: Rarity | H2: Ability | I2: Comment | J2: Formula | K2: Have illustration | L2: Suggested cost | M2: Demo | N2: Test 1 | O2: ="Booster Pack - Blightsilver / "&COUNTIF(N3:N545,"Yes") | P2: ="Booster Pack - Unseen Presence / "&COUNTIF(O3:O545,"Yes") | Q2: ="Booster Pack - Wind of Dominance / "&COUNTIF(P3:P545,"Yes")
A3: Trap Hole | B3: Trap | C3: 0 | G3: 1 | H3: Flip 3 coins. Attacker loses 20 Crystals per Head. | I3: Grammar: coins plural; per Head wording. | K3: Yes | M3: Yes | O3: Yes
A4: Hostage | B4: Trap | C4: 200 | G4: 2 | H4: The trapper reveals 1 own cell. This turn: attacker cannot target that cell. | I4: wording polish | K4: Yes | M4: Yes | O4: Yes
A5: Bait | B5: Trap | C5: 0 | G5: 1 | H5: The trapper chooses one other cell on their field and reveal it | I5: wording polish | K5: Yes | M5: Yes | O5: Yes
A6: Blackmail | B6: Trap | C6: 0 | G6: 2 | H6: The attacker choose either discarding 1 Tech Card or end the turn immediately | K6: Yes | M6: Yes | O6: Yes
A7: Cursed Reflection | B7: Trap | C7: 500 | G7: 3 | H7: Swap the attacker's ATK and DEF until the trapper’s turn ends | I7: ATK&DEF→ATK and DEF | K7: Yes | M7: Yes | P7: Yes
A8: Explosive Barrels | B8: Trap | C8: 0 | G8: 5 | H8: Destroy the attacking unit. Trapper also pay the same cost as attacker. | K8: Yes | M8: Yes | Q8: Yes
A9: Hypnosis | B9: Trap | C9: 800 | G9: 4 | H9: The attacking unit cannot attack during their next turn | K9: Yes | M9: Yes | O9: Yes
A10: Flame Trap | B10: Trap | C10: 250 | G10: 2 | H10: Attacking unit get -10 ATK permanently | K10: Yes | M10: Yes | P10: Yes
A11: Echo Barrier | B11: Trap | C11: 1000 | G11: 3 | H11: This turn, attacker cannot perform any more attack. | K11: Yes | M11: Yes | P11: Yes
A12: Mana Drain | B12: Trap | C12: 200 | G12: 2 | H12: Attacking player loses 300 Crystals. Increase trapper’s Crystal by that amount | K12: Yes
A13: Defensive Pheromone | B13: Trap | C13: 500 | G13: 3 | H13: The trapper swaps 1 'Armored' Nature card on their side with this cell, then repeat Reckoning. | I13: wording polish | K13: Yes | M13: Yes | P13: Yes
A14: Spike Trap | B14: Trap | C14: 1500 | G14: 5 | H14: Destroy the attacking unit | K14: Yes | M14: Yes | Q14: Yes
A15: Snare Trap | B15: Trap | C15: 500 | G15: 4 | H15: The attacking unit's ability becomes None until attacker’s next turn ends | K15: Yes | M15: Yes | Q15: Yes
A16: Brainwash | B16: Trap | C16: 1500 | G16: 5 | H16: The attacker chooses their own ally as an attack target | I16: wording polish | K16: Yes | M16: Yes | P16: Yes
A17: Bunker | B17: Trap | C17: 600 | G17: 4 | H17: Attacker cannot target surrounding cells until the end of this turn. | K17: Yes | M17: Yes | Q17: Yes
A18: Foul Gas | B18: Trap | C18: 0 | G18: 3 | H18: -5 ATK to all the attacking player’s units until the end of this turn | K18: Yes | M18: Yes | O18: Yes
A19: Choking Gas | B19: Trap | C19: 800 | G19: 4 | H19: -20 ATK to all the attacking player’s units until the end of this turn | K19: Yes
A20: Potent Poison | B20: Trap | C20: 600 | G20: 4 | H20: Attacking unit permanently lose 5 ATK and DEF. It lose more 5 ATK and DEF for each trap cards in trapper’s void | I20: ATK&DEF→ATK and DEF | K20: Yes
A21: Acid Trap Hole | B21: Trap | C21: 0 | G21: 1 | H21: Flip 2 coins. Attacker loses 50 Crystals per Head. | I21: Grammar: coins plural; per Head wording. | K21: Yes | M21: Yes | O21: Yes
A22: Lava Trap Hole | B22: Trap | C22: 50 | G22: 2 | H22: Flip 3 coins. Attacker loses 100 Crystals per Head. | I22: Grammar: coins plural; per Head wording. | K22: Yes
A23: Fissure | B23: Trap | C23: 100 | G23: 3 | H23: Attacking player loses 200 Crystals | K23: Yes
A24: Soul Blast | B24: Trap | C24: 1000 | G24: 5 | H24: Attacking player lose 150 Crystals for each unit cards in trapper’s void | K24: Yes
A25: Grudge | B25: Trap | C25: 850 | G25: 2 | H25: -10 ATK to the attacking monster permanently for each unit cards in trapper’s void | K25: Yes
A26: Anti-virus | B26: Trap | C26: 600 | G26: 1 | H26: If attacker is Bio, flip a coin. Heads: destroy it. Always Heads, if trapper’s Crystal is 1000 or less. | I26: Head→Heads | K26: Yes
A27: Witch Hunt | B27: Trap | C27: 600 | G27: 1 | H27: If attacker is Arcane, flip a coin. Heads: destroy it. Always Heads, if trapper’s Crystal is 1000 or less. | I27: Head→Heads | K27: Yes
A28: Standoff | B28: Trap | C28: 600 | G28: 1 | H28: If attacker is Anima, flip a coin. Heads: destroy it. Always Heads, if trapper’s Crystal is 1000 or less. | I28: Head→Heads | K28: Yes
A29: Apple of Adam | B29: Trap | C29: 600 | G29: 1 | H29: If attacker is Divine, flip a coin. Heads: destroy it. Always Heads, if trapper’s Crystal is 1000 or less. | I29: Head→Heads | K29: Yes
A30: Purify | B30: Trap | C30: 600 | G30: 1 | H30: If attacker is Chaos, flip a coin. Heads: destroy it. Always Heads, if trapper’s Crystal is 1000 or less. | I30: Head→Heads | K30: Yes
A31: Solar Flare | B31: Trap | C31: 600 | G31: 1 | H31: If attacker is Cosmic, flip a coin. Heads: destroy it. Always Heads, if trapper’s Crystal is 1000 or less. | I31: Head→Heads | K31: Yes
A32: Hunting Season | B32: Trap | C32: 600 | G32: 1 | H32: If attacker is Nature, flip a coin. Heads: destroy it. Always Heads, if trapper’s Crystal is 1000 or less. | I32: Head→Heads | K32: Yes
A33: Dart Trap | B33: Trap | C33: 300 | G33: 2 | H33: If the attacking monster is the first one in that turn, destroy it. | K33: Yes
A34: Science Cage | B34: Trap | C34: 800 | G34: 3 | H34: If attacking unit Is Bio affinity, end their turn immediately. Remove all flags from it. | K34: Yes
A35: Loop Hole | B35: Trap | C35: 800 | G35: 3 | H35: If attacker is Arcane, end the their turn immediately. | K35: Yes
A36: Talisman of Light | B36: Trap | C36: 800 | G36: 3 | H36: If attacker is Chaos, -50 ATK to that monster permanently | K36: Yes
A37: Forbidden Grail | B37: Trap | C37: 800 | G37: 3 | H37: If attacker is Divine, -50 DEF to that monster permanently | K37: Yes
A38: Electric Fence | B38: Trap | C38: 800 | G38: 3 | H38: If attacker is Nature, it cannot attack until attacker’s next turn ends | K38: Yes
A39: Discourage | B39: Trap | C39: 800 | G39: 3 | H39: If attacker Is Anima -15 ATK to all Exposed units on their field until attacker’s next turn ends | I39: wording polish | K39: Yes
A40: Galaxy Toll | B40: Trap | C40: 800 | G40: 3 | H40: If attacker is Cosmic, foe loses 1000 Crystals | I40: wording polish | K40: Yes
A41: Union Cage | B41: Trap | C41: 1200 | G41: 3 | H41: If attacking unit Is Union card, that unit cannot attack until the attacker’s next turn ends. | K41: Yes
A42: Plunder | B42: Trap | C42: 1500 | G42: 4 | H42: The attacker choose to let trapper receive 2000 Crystals, or destroy the attacking monster. | K42: Yes
A43: Decoy Puppet | B43: Trap | C43: 100 | G43: 2 | H43: This turn, attacker cannot perform any more attack using unit with 400 or less cost. | K43: Yes | M43: Yes | P43: Yes
A44: Hard Scale | B44: Trap | C44: 700 | G44: 1 | H44: All of trapper’s unit gain +5 DEF in Reckoning until attacker’s next turn ends | K44: Yes | M44: Yes | P44: Yes
A45: Steel Scale | B45: Trap | C45: 1200 | G45: 1 | H45: All of trapper’s units gain +15 DEF in Reckoning until attacker’s next turn ends
A46: Trick Door | B46: Trap | C46: 1500 | G46: 1 | H46: The trapper selects 1 unit and swap or relocate to any cell. Repeat Reckoning if it’s this cell. | I46: wording polish
A47: Boiling Oil | B47: Trap | C47: 950 | G47: 1 | H47: All of attacker’s unit get -10 ATK in Reckoning until this turn’s end
A48: Lightning Rod | B48: Trap | C48: 0 | G48: 3 | H48: Foe lose 1000 Crystals if they target this card with any Tech card | I48: wording polish
A49: Dreamcatcher | B49: Trap | C49: 2000 | G49: 5 | H49: When foe use a Tech card, this card can be triggered. That Tech card effect is cancelled. | I49: wording polish
A50: Stumble | B50: Trap | C50: 100 | G50: 1 | H50: Attacker ends their turn immediately. If attacker has any remaining attack, they are transferred to their next turn. | I50: subject-verb grammar
A51: Ruckus | C51: 0 | G51: 1 | H51: Until the end of trapper’s turn, All exposed Bio monster gain +5 ATK
A52: Red Card | B52: Trap | C52: 0 | G52: 2 | H52: Flip 2 coins. Both Heads: that unit cannot attack until attacker's next turn ends. | I52: Fixed incomplete sentence. | K52: Yes | M52: Yes | P52: Yes
A53: Counter Punch | C53: 0 | G53: 2 | H53: Attacking unit get -5 DEF until the end of trapper’s turn
A54: Counter Tackle | C54: 500 | G54: 3 | H54: Attacking unit get -15 DEF until the end of trapper’s turn
A55: Street Joke | B55: Trap | C55: 0 | G55: 1 | H55: Reveal 1 of trapper’s cell, they receive 100 Crystal | K55: Yes | M55: Yes | O55: Yes
A56: Alarm | B56: Trap | C56: 0 | G56: 1 | H56: This turn: All trapper’s Anima monster gain +10 DEF in Reckoning | I56: wording polish | K56: Yes | M56: Yes | O56: Yes
A57: Protective Instinct | C57: 0 | G57: 1 | H57: The trapper selects 1 Nature unit. Until the end of trapper’s turn, that card gain +10 ATK | I57: wording polish
A58: Self-destruct | B58: Trap | C58: 0 | G58: 2 | H58: The trapper selects 1 of their unit. +10 ATK until trapper’s turn ends, but also destroy it. Trapper pay no Crystal cost. | I58: wording polish | K58: Yes | M58: Yes | Q58: Yes
A59: Bounty | C59: 0 | G59: 2 | H59: Until the end of trapper’s turn, if trapper destroy that unit, they receive Crystal equal to half of the unit’s cost
A60: Pepper Spray | B60: Trap | C60: 0 | G60: 1 | H60: Flip 2 coins. Heads: attacker loses 5 ATK per Head until attacker's next turn ends. | I60: Grammar; removed double negative 'lose -5'. | K60: Yes | M60: Yes | P60: Yes
A61: Share the Pain | C61: 0 | G61: 5 | H61: If trapper has 1000 or less Crystal, drain Crystal from attacker until both players have same amount of Crystals | I61: wording polish
A62: Tripwire | C62: 300 | H62: Destroy the attacker with 20 or less ATK. Attacker side pay no Crystal cost. | I62: wording polish

Sheet Tech
A1: Table 1
A2: Card Name | B2: Card Type | C2: Cost | D2: ATK | E2: DEF | F2: Affinity | G2: Rarity | H2: Ability | I2: Comment | J2: Formula | K2: Illustration | L2: Suggested cost | M2: Demo | N2: Test 1 | O2: ="Booster Pack - Blightsilver / "&COUNTIF(N3:N556,"Yes") | P2: ="Booster Pack - Unseen Presence / "&COUNTIF(O3:O556,"Yes") | Q2: ="Booster Pack - Wind of Dominance / "&COUNTIF(P3:P556,"Yes")
A3: Welcoming Door | B3: Tech | C3: 0 | G3: 1 | H3: Reveal any own cell. | I3: Shortened; cell terminology. | K3: Yes
A4: Spy | B4: Tech | C4: 0 | G4: 1 | H4: Reveal 1 of foe’s cell | K4: Yes | M4: Yes | O4: Yes
A5: Ceasefire | B5: Tech | C5: 0 | G5: 3 | H5: Both players skip 1 turn (tax is forced to apply) | K5: Yes
A6: Make Friend | B6: Tech | C6: 0 | G6: 5 | H6: Both players select 1 monster from their field. Those monster cannot attack until this player’s next turn ends | K6: Yes
A7: Double Spy | B7: Tech | C7: 0 | G7: 2 | H7: Only trigger if this player have Spy card in the void. Reveal 2 cell on foe's side of the field. | I7: square→cell | K7: Yes
A8: Invisible Spy | B8: Tech | C8: 0 | G8: 3 | H8: Only trigger if this player have Double Spy card in the void. Reveal 2 cell on foe's side of the field. | I8: square→cell | K8: Yes
A9: Corrupted Spy | B9: Tech | C9: 0 | G9: 4 | H9: Reveal 3 foe cells. Pay 700 Crystal cost per trap or unit found. | I9: Shortened; cell/Crystal cost. | K9: Yes
A10: Tease | B10: Tech | C10: 0 | G10: 2 | H10: Foe choose and reveal 1 of their cell | K10: Yes | M10: Yes | P10: Yes
A11: Bribe | B11: Tech | C11: 0 | G11: 3 | H11: Foe can choose to reveal a unit card and receive 700 Crystals or do nothing | K11: Yes | M11: Yes | O11: Yes
A12: Release Mutagen | B12: Tech | C12: 0 | G12: 4 | H12: Add Mutagen flag to 1 of this player’s unit | I12: wording polish | K12: Yes | M12: Yes | P12: Yes
A13: Prayer | B13: Tech | C13: 0 | G13: 4 | H13: Once: until foe’s turn ends: prevent Divine card from being destroyed | I13: wording polish | K13: Yes | M13: Yes | P13: Yes
A14: Arcane Nova | B14: Tech | C14: 3000 | G14: 5 | H14: Destroy up to 3 Exposed foe units (no cost is paid). This player discard all of their Tech cards afterward. | I14: wording polish | K14: Yes
A15: Rift Strike | B15: Tech | C15: 2000 | G15: 3 | H15: Choose 1 Exposed foe unit. Destroy other Exposed units in its row. Foe pays no Crystal cost. | I15: Shortened; Exposed/cell/Crystal cost. | K15: Yes
A16: Great Diplomacy | B16: Tech | C16: 1000 | G16: 4 | H16: Select up to 5 of their units and reveal them. | I16: wording polish | K16: Yes | M16: Yes | Q16: Yes
A17: War Supply | B17: Tech | C17: 1000 | G17: 3 | H17: This player’s units get +10 ATK and DEF in Reckoning until turn’s end | I17: ATK&DEF→ATK and DEF | K17: Yes | M17: Yes | O17: Yes
A18: Harsh Training | B18: Tech | C18: 500 | G18: 2 | H18: +10 ATK permanently to one of this player's unit. | K18: Yes
A19: Illegal Steroid | B19: Tech | C19: 1000 | G19: 4 | H19: +30 ATK for 1 unit until the end of this turn. | K19: Yes
A20: Secret Dagger | B20: Tech | C20: 600 | G20: 3 | H20: Can only be used on face-down unit. Turn that card exposed and +15 ATK until the end of this turn. | I20: wording polish | K20: Yes
A21: Garrison | B21: Tech | C21: 1500 | G21: 4 | H21: Until foe's turn ends: +20 DEF to all this player's cards in Reckoning | K21: Yes
A22: Bulletproof Vest | B22: Tech | C22: 850 | G22: 3 | H22: +15 DEF permanently for 1 Exposed unit. If use on face-down unit, flip it up. | I22: wording polish | K22: Yes
A23: Siege Cannon | B23: Tech | C23: 1000 | G23: 5 | H23: This turn: once, foe’s defending unit is destroyed. | I23: shortened | K23: Yes | M23: Yes | Q23: Yes
A24: Silence Agent | B24: Tech | C24: 2000 | G24: 4 | H24: Destroy 1 of foe’s Exposed unit | I24: wording polish | K24: Yes
A25: Accident | B25: Tech | C25: 1000 | G25: 3 | H25: Destroy 1 Exposed foe unit. If none, foe chooses 1 to Expose. Foe pays no Crystal cost. | I25: Shortened; Exposed terminology. | K25: Yes | M25: Yes | Q25: Yes
A26: Berserk | B26: Tech | C26: 2000 | G26: 5 | H26: Choose 1 Exposed ally. It gets 1 extra attack but is your only attacker this turn. Cannot use if you already attacked. | I26: Shortened; Exposed terminology. | K26: Yes
A27: Radar | B27: Tech | C27: 600 | G27: 1 | H27: Reveal 3 of foe’s cell | K27: Yes | M27: Yes | O27: Yes
A28: Palace Party | B28: Tech | C28: 500 | G28: 2 | H28: This player reveal 1 face-down unit. Foe must reveal 1 of their face-down unit (if any) | K28: Yes
A29: Essence Transfer | B29: Tech | C29: 700 | G29: 5 | H29: Choose 1 unit. Move all its ATK and DEF bonuses or debuffs to another ally unit. | I29: ATK&DEF→ATK and DEF | K29: Yes
A30: Blood Ritual | B30: Tech | C30: 1200 | G30: 4 | H30: Destroy 1 own card (no Crystal cost). Choose 1 Exposed foe unit; its ATK and DEF become 0 permanently. | I30: Fixed 'the this'; terminology. | K30: Yes
A31: Arcane Duplication | B31: Tech | C31: 1000 | G31: 5 | H31: Choose 1 unit. Create a token copy on an empty cell. Destroy the token at end of your next turn. | I31: Removed dangling 'This player.'; shortened. | K31: Yes
A32: Time Travel | B32: Tech | C32: 1800 | G32: 5 | H32: Once only, revive 1 unit to any unoccupied or empty cell in Exposed position. Double its Crystal cost. | I32: wording polish | K32: Yes
A33: Resurrection | B33: Tech | C33: 1500 | G33: 4 | H33: Once: revive 1 unit. It has no ATK,DEF, or ability. | I33: wording polish | K33: Yes | M33: Yes | Q33: Yes
A34: Tech Copy | B34: Tech | C34: 1000 | G34: 3 | H34: Foe show 1 Tech card in their hand. Add a copy of that card into this player's Tech Stack. | I34: wording polish
A35: Force Shield | B35: Tech | C35: 600 | G35: 2 | H35: Select 1card. It is not destroyed until the end of foe's turn | I35: wording polish
A36: Wisp Light | B36: Tech | C36: 250 | G36: 3 | H36: Destroy as many ally ‘wisp’ units. Reveal that much cells on foe's field.
A37: Lucky Day | B37: Tech | C37: 300 | G37: 2 | H37: Flip a coin. Heads: receive 600 Crystals. Always Heads, if trapper’s Crystal is 1000 or less. | I37: Head→Heads
A38: Immortal Blood | B38: Tech | C38: 1000 | G38: 3 | H38: Revive 1 immortal vampire or vampire servant.
A39: Yin Yang Swap | B39: Tech | C39: 1200 | G39: 4 | H39: Swap ATK and DEF on 1 Exposed unit until the end of this turn | I39: ATK&DEF→ATK and DEF
A40: Coin on the Street | B40: Tech | C40: 0 | G40: 1 | H40: Receive 20 Crystals
A41: Bank Note on the Street | B41: Tech | C41: 0 | G41: 2 | H41: Receive 50 Crystals
A42: Casual Gambling | B42: Tech | C42: 0 | G42: 1 | H42: Flip a coin. Heads: receive 100 Crystals. | I42: Head→Heads
A43: Degen Gambling | B43: Tech | C43: 0 | G43: 2 | H43: Flip a coin. Heads: receive 200 Crystals. Tails: lose 400 Crystals | I43: Head→Heads; Tail→Tails
A44: Gift | B44: Tech | C44: 0 | G44: 1 | H44: Foe receive 50 Crystals
A45: Hired Spanker | B45: Tech | C45: 0 | G45: 2 | H45: Until foe's turn ends: if foe attack the bluffed cell, foe receive 1000 Crystals. | I45: wording polish
A46: Tax Avoidance | B46: Tech | C46: 0 | G46: 1 | H46: End this player’s turn without paying tax (the tax penalty still doubles)
A47: Compensation | B47: Tech | C47: 0 | G47: 1 | H47: This turn, whenever this player attack a Dead End, they receive 20 Crystals
A48: Phony Fight | B48: Tech | C48: 500 | G48: 1 | H48: -10 DEF to 1 Exposed unit on the field until the end of this turn. Foe receive 500 Crystals | I48: wording polish
A49: Facetious | B49: Tech | C49: 0 | G49: 1 | H49: Send an emoticon bubble to another player once
A50: Telepathy | B50: Tech | C50: 100 | G50: 1 | H50: Send a very short message to foe once.
A51: Borrow | B51: Tech | C51: 0 | G51: 1 | H51: Receive 200 Crystals. At the end of this player’s turn, they lose 300 Crystals
A52: Flimsy Axe | B52: Tech | C52: 200 | G52: 1 | H52: Flip a coin. Heads: +5 ATK to 1 ally unit until this turn ends. | I52: Head→Heads
A53: Flimsy Shield | B53: Tech | C53: 200 | G53: 1 | H53: Flip a coin. Heads: +5 DEF to 1 ally unit until this turn ends. | I53: Head→Heads
A54: All-out Tactics | B54: Tech | C54: 600 | G54: 1 | H54: +10 ATK to one ally unit permanently. But its DEF becomes 0 permanently.
A55: Fair Fight | B55: Tech | C55: 500 | G55: 2 | H55: Both players select 1 of their unit. They gain +10 ATK and DEF permanently | I55: ATK&DEF→ATK and DEF
A56: Greater Telepathy | B56: Tech | C56: 400 | G56: 2 | H56: Send a medium length message to foe once.
A57: Loan | B57: Tech | C57: 0 | G57: 2 | H57: Receive 600 Crystals. At this player’s next turn’s end: lose 800 Crystals
A58: Old Spear | B58: Tech | C58: 450 | G58: 2 | H58: +5 ATK to 1 ally unit until this turn ends.
A59: Old Shield | B59: Tech | C59: 450 | G59: 2 | H59: +5 DEF to 1 ally unit until this turn ends.
A60: Provoke | B60: Tech | C60: 200 | G60: 4 | H60: At the end of foe’s turn, foe must attack the selected cell first.
A61: Supreme Telepathy | B61: Tech | C61: 700 | G61: 5 | H61: Send a long message to foe once.
A62: Mortgage | B62: Tech | C62: 0 | G62: 2 | H62: Receive 1200 Crystals. At the end of this player’s turn, lose 1500 Crystals
A63: Big Finger | B63: Tech | C63: 0 | G63: 4 | H63: Send a very big improper emoticon bubble to foe
A64: Big Love | B64: Tech | C64: 0 | G64: 4 | H64: Send a very big lovely emoticon bubble to foe
A65: Pretify | B65: Tech | C65: 1000 | G65: 3 | H65: +20 DEF permanently to ally unit or foe’s Exposed unit. But its ATK becomes 0 permanently. | I65: wording polish
A66: Stone Skin | B66: Tech | C66: 800 | G66: 2 | H66: +20 DEF permanently to ally unit. But its ATK becomes 0 permanently.
A67: Battle Royale | B67: Tech | C67: 1000 | G67: 5 | H67: Both players select 1 of their unit. They gain +30 ATK and DEF | I67: ATK&DEF→ATK and DEF
A68: Guerrilla Tactics | B68: Tech | C68: 1500 | G68: 3 | H68: Until foe's turn ends: If they attack a non-unit card, flip a coin. Heads: destroy the attacking unit. | I68: Head→Heads
A69: Toll | B69: Tech | C69: 1000 | G69: 2 | H69: Until foe's turn ends: they have to pay 500 Crystal tax to perform an attack. | I69: wording polish
A70: Skull Amulet | B70: Tech | C70: 300 | G70: 1 | H70: +5 ATK permanently to 1 Chaos card.
A71: Might | B71: Tech | C71: 300 | G71: 1 | H71: +10 ATK to 1 ally Anima card until this turn ends
A72: Arcane Knowledge | B72: Tech | C72: 500 | G72: 2 | H72: +5 ATK and DEF to 1 ally Arcane unit until the end of foe’s turn. | I72: ATK&DEF→ATK and DEF
A73: Forest Fire | B73: Tech | C73: 2000 | G73: 4 | H73: Destroy all Nature cards on foe’s field. Discard all of this player’s Tech cards.
A74: Black Hole | B74: Tech | C74: 2000 | G74: 5 | H74: Destroy all Cosmic cards on foe's field. Discard all your Tech cards. | I74: Cosmo→Cosmic typo; shorten.
A75: Holy Arrival | B75: Tech | C75: 2000 | G75: 5 | H75: Destroy all Chaos cards on foe’s field. Discard all of this player’s Tech cards.
A76: Corrupted Heaven | B76: Tech | C76: 2000 | G76: 5 | H76: Destroy all Divine cards on foe’s field. Discard all of this player’s Tech cards.
A77: Earthquake | B77: Tech | C77: 2000 | G77: 5 | H77: Destroy all Anima cards on foe’s field. Discard all of this player’s Tech cards.
A78: Lab Destruction | B78: Tech | C78: 2000 | G78: 5 | H78: Destroy all Bio cards on foe’s field. Discard all of this player’s Tech cards.
A79: Anti-magic Field | B79: Tech | C79: 2000 | G79: 5 | H79: Destroy all Arcane cards on foe’s field. Discard all of this player’s Tech cards.
A80: Air Shower | B80: Tech | C80: 1200 | G80: 4 | H80: Clear all flags on the field
A81: Mining Tax | B81: Tech | C81: 2000 | G81: 3 | H81: Until the end of foe’s turn, if any player attacks a Dead End, that player loses 200 Crystals
A82: Ouija | B82: Tech | C82: 1000 | G82: 3 | H82: Reveal foe’s cells up to number of this player’s unit in the void.
A83: Deep Mine | B83: Tech | C83: 500 | G83: 2 | H83: Flip a coin. Heads: reveal 2 cell on foe's side of the field | I83: square→cell; Head→Heads
A84: Gold Panning | B84: Tech | C84: 250 | G84: 1 | H84: Flip a coin. Heads: reveal 1 cell on foe's side of the field | I84: square→cell; Head→Heads
A85: Flashlight | B85: Tech | C85: 1500 | G85: 4 | H85: Reveal 1 column on foe’s side. Cannot perform attack this turn. Cannot use this card if already attacked this turn.
A86: Lantern | B86: Tech | C86: 1000 | G86: 3 | H86: Reveal 2 adjacent cells on foe's side of the field.
A87: GPS Tracker | B87: Tech | C87: 800 | G87: 2 | H87: Reveal 2 adjacent cells next to Exposed unit on foe's side of the field. | I87: wording polish
A88: Blessing | B88: Tech | C88: 200 | G88: 2 | H88: Clear all flags from 1 ally unit
A89: Bright Sun | B89: Tech | C89: 1500 | G89: 3 | H89: Clear all flags from all cards on the field
A90: Rugpull | B90: Tech | C90: 500 | G90: 5 | H90: Both players lose 2000 Crystals. Discard all Tech in this player’s hands. | I90: wording polish
A91: Crack the Whip | B91: Tech | C91: 1000 | G91: 2 | H91: Once: this player’s attacking unit can attack twice. But it cannot attack again until the end of this player’s next turn. | I91: wording polish | K91: Need Revise
A92: Full open fire | B92: Tech | C92: 1500 | G92: 4 | H92: Both players gain 2 additional attack for one of their turn.
A93: Service Charge | B93: Tech | C93: 300 | G93: 1 | H93: Until the end of foe's turn. Foe have to pay 50 Crystal tax to perform an attack.
A94: Lazy Scout | B94: Tech | C94: 200 | G94: 1 | H94: Reveal 1 foe’s cell. This player cannot perform any attack. Cannot use this card if already attacked.
A95: Last Gambit | B95: Tech | C95: 0 | G95: 1 | H95: If this player have 5 or less card on the field, destroy 1 foe’s card.
A96: Trash Penalty | B96: Tech | C96: 0 | G96: 1 | H96: Foe choose either clearing all of their bluffs or take 500 damage
A97: Silence Zone | B97: Tech | C97: 1000 | G97: 1 | H97: Clear all bluffs from both players. No one can use bluff ever again during this duel.
A98: Big Mouth | B98: Tech | C98: 0 | G98: 1 | H98: Select 1 cell. Bluff on that cell becomes large permanently
A99: Bare Fist Fight | B99: Tech | C99: 0 | G99: 1 | H99: Both players select and discard 1 Tech card from their hand. | I99: wording polish
A100: Mine Detector | B100: Tech | C100: 500 | G100: 2 | H100: Reveal 1 card on foe’s field. If it’s a trap, destroy it and gain 200 Crystals
...

Sheet Count
A1: Table 1
A2: Rarity | B2: Expected | C2: Percentage of Pool | D2: Notes | E2: Actual
A3: Common | B3: 52 | C3: 0.347 | D3: Filler / staple cards | E3: =_xlfn.COUNTIFS('Unit'!$L$3:$L$568,"Yes",'Unit'!$G$3:$G$568,1)+_xlfn.COUNTIFS('Trap'!$L$3:$L$545,"Yes",'Trap'!$G$3:$G$545,1)+_xlfn.COUNTIFS('Tech'!$L$3:$L$556,"Yes",'Tech'!$G$3:$G$556,1)
A4: Uncommon | B4: 48 | C4: 0.337 | D4: - | E4: =_xlfn.COUNTIFS('Unit'!$L$3:$L$568,"Yes",'Unit'!$G$3:$G$568,2)+_xlfn.COUNTIFS('Trap'!$L$3:$L$545,"Yes",'Trap'!$G$3:$G$545,2)+_xlfn.COUNTIFS('Tech'!$L$3:$L$556,"Yes",'Tech'!$G$3:$G$556,2)
A5: Rare | B5: 27 | C5: 0.167 | D5: - | E5: =_xlfn.COUNTIFS('Unit'!$L$3:$L$568,"Yes",'Unit'!$G$3:$G$568,3)+_xlfn.COUNTIFS('Trap'!$L$3:$L$545,"Yes",'Trap'!$G$3:$G$545,3)+_xlfn.COUNTIFS('Tech'!$L$3:$L$556,"Yes",'Tech'!$G$3:$G$556,3)
A6: Legendary | B6: 16 | C6: 0.1 | D6: Strong but not broken | E6: =_xlfn.COUNTIFS('Unit'!$L$3:$L$568,"Yes",'Unit'!$G$3:$G$568,4)+_xlfn.COUNTIFS('Trap'!$L$3:$L$545,"Yes",'Trap'!$G$3:$G$545,4)+_xlfn.COUNTIFS('Tech'!$L$3:$L$556,"Yes",'Tech'!$G$3:$G$556,4)
A7: Exotic | B7: 9 | C7: 0.053 | D7: Very desirable | E7: =_xlfn.COUNTIFS('Unit'!$L$3:$L$568,"Yes",'Unit'!$G$3:$G$568,5)+_xlfn.COUNTIFS('Trap'!$L$3:$L$545,"Yes",'Trap'!$G$3:$G$545,5)+_xlfn.COUNTIFS('Tech'!$L$3:$L$556,"Yes",'Tech'!$G$3:$G$556,5)
A11: Rarity | B11: Expected | E11: Actual
A12: Blightsilver | B12: 60 | E12: =_xlfn.COUNTIFS('Unit'!$N$3:$N$568,"Yes")+_xlfn.COUNTIFS('Trap'!$N$3:$N$545,"Yes")+_xlfn.COUNTIFS('Tech'!$N$3:$N$556,"Yes")
A13: Unseen Presence | B13: 60 | E13: =_xlfn.COUNTIFS('Unit'!$O$3:$O$568,"Yes")+_xlfn.COUNTIFS('Trap'!$O$3:$O$545,"Yes")+_xlfn.COUNTIFS('Tech'!$O$3:$O$556,"Yes")
A14: Wind of Dominance | B14: 60 | E14: =_xlfn.COUNTIFS('Unit'!$P$3:$P$568,"Yes")+_xlfn.COUNTIFS('Trap'!$P$3:$P$545,"Yes")+_xlfn.COUNTIFS('Tech'!$P$3:$P$556,"Yes")

Sheet Rule
A1: Table 1
B2: Old | C2: New
A3: 1 | B3: Foe | C3: foe
A4: 2 | B4: Battle calculation | C4: Reckoning
A5: 3 | B5: Cannot attack | C5: wait
A6: 4 | B6: ATK&DEF | C6: ATK&DEF
A7: 5 | B7: If head | C7: Head:
A8: 6 | B8: If tail | C8: Tail:
A9: 7 | B9: Square, grid | C9: cell
A10: 8 | B10: exposed | C10: Exposed
