Workbook

Sheet Affinity
A1: Table 1
A2: Affinity | B2: Key strength
A3: Divine | B3: High defense, Anti-Chaos bonus
A4: Chaos | B4: High cost, powerful units, Especially weak to Divine
A5: Arcane | B5: Spending a lot of Crystal to maximize power in short time. A glass cannon.
A6: Nature | B6: Balanced
A7: Bio | B7: Few unit, mutate to other or attack a lot of times, Tech heavy
A8: Cosmic | B8: High discovery capacity, Tech heavy
A9: Anima | B9: Low cost, swarming

Sheet Unit
A1: Table 1
A2: Card Name | B2: Card Type | C2: Cost | D2: ATK | E2: DEF | F2: Affinity | G2: Rarity | H2: Ability | I2: Formula | J2: Have illustration | K2: Suggested cost | L2: Demo | M2: Test 1 | N2: ="Booster Pack - Blightsilver / "&COUNTIF(N3:N599,"Yes") -> Booster Pack - Blightsilver / 49 | O2: ="Booster Pack - Unseen Presence / "&COUNTIF(O3:O599,"Yes") -> Booster Pack - Unseen Presence / 50 | P2: ="Booster Pack - Wind of Dominance / "&COUNTIF(P3:P599,"Yes") -> Booster Pack - Wind of Dominance / 50
A3: Pyromancer | B3: Unit | C3: 900 | D3: 80 | E3: 0 | F3: Arcane | G3: 4 | H3: +30 ATK vs Nature Affinity | J3: Yes | K3: =(D3*6)+(E3*4) -> 480 | L3: Yes | P3: Yes
A4: Angel Gatekeeper | B4: Unit | C4: 1000 | D4: 40 | E4: 90 | F4: Divine | G4: 4 | H4: +50 ATK vs Chaos Affinity | J4: Yes | K4: =(D4*6)+(E4*4) -> 600 | L4: Yes | N4: Yes | P4: Yes
A5: Wandering Swordsman | B5: Unit | C5: 600 | D5: 60 | E5: 60 | F5: Anima | G5: 3 | H5: None | J5: Yes | K5: =(D5*6)+(E5*4) -> 600 | L5: Yes | N5: Yes | P5: Yes
A6: Huntress of Green Glade | B6: Unit | C6: 800 | D6: 50 | E6: 50 | F6: Anima | G6: 3 | H6: Immune to 0-cost Traps | J6: Yes | K6: =(D6*6)+(E6*4) -> 500 | L6: Yes | N6: Yes
A7: Fierce Gladiator | B7: Unit | C7: 1000 | D7: 70 | E7: 90 | F7: Anima | G7: 3 | H7: +200 Crystal if successfully defended | J7: Yes | K7: =(D7*6)+(E7*4) -> 780 | L7: Yes
A8: Canyon Warg | B8: Unit | C8: 750 | D8: 70 | E8: 30 | F8: Nature | G8: 3 | H8: None | J8: Yes | K8: =(D8*6)+(E8*4) -> 540 | L8: Yes | P8: Yes
A9: Armored Bee | B9: Unit | C9: 480 | D9: 30 | E9: 0 | F9: Nature | G9: 2 | H9: +60 DEF until the end of that turn once | J9: Yes | K9: =(D9*6)+(E9*4) -> 180 | L9: Yes | N9: Yes
A10: Armored Rhino | B10: Unit | C10: 720 | D10: 60 | E10: 85 | F10: Nature | G10: 3 | H10: None | J10: Yes | K10: =(D10*6)+(E10*4) -> 700 | L10: Yes | O10: Yes
A11: Lightbringer | B11: Unit | C11: 1200 | D11: 80 | E11: 40 | F11: Divine | G11: 3 | H11: +100 DEF vs Chaos Affinity | J11: Yes | K11: =(D11*6)+(E11*4) -> 640
A12: Chaotic Wisp | B12: Unit | C12: 100 | D12: 20 | E12: 0 | F12: Chaos | G12: 1 | H12: None | J12: Yes | K12: =(D12*6)+(E12*4) -> 120 | L12: Yes
A13: Foul Wisp | B13: Unit | C13: 100 | D13: 0 | E13: 25 | F13: Chaos | G13: 1 | H13: None | J13: Yes | K13: =(D13*6)+(E13*4) -> 100 | L13: Yes | N13: Yes
A14: Doom Wisp | B14: Unit | C14: 100 | D14: 15 | E14: 15 | F14: Chaos | G14: 1 | H14: None | J14: Yes | K14: =(D14*6)+(E14*4) -> 150 | L14: Yes | N14: Yes
A15: Night Whisperer | B15: Unit | C15: 900 | D15: 30 | E15: 30 | F15: Chaos | G15: 3 | H15: +30 ATK&DEF for each exposed ‘wisp’ card on your side | J15: Yes | K15: =(D15*6)+(E15*4) -> 300 | L15: Yes | O15: Yes
A16: Leorudus the Warlord | B16: Unit | C16: 1150 | D16: 80 | E16: 80 | F16: Anima | G16: 5 | H16: +20 ATK&DEF for each other exposed Anima card on your side | J16: Yes | K16: =(D16*6)+(E16*4) -> 800 | L16: Yes | O16: Yes
A17: Aether Warden | B17: Unit | C17: 800 | D17: 30 | E17: 110 | F17: Divine | G17: 3 | H17: In Reckoning if it defends, attacker loses 300 Crystals | J17: Yes | K17: =(D17*6)+(E17*4) -> 620
A18: Void Stalker | B18: Unit | C18: 720 | D18: 65 | E18: 25 | F18: Chaos | G18: 3 | H18: +20 ATK if it attacks an exposed card. | J18: Yes | K18: =(D18*6)+(E18*4) -> 490 | L18: Yes | N18: Yes
A19: Swarmcaller | B19: Unit | C19: 950 | D19: 45 | E19: 45 | F19: Nature | G19: 4 | H19: +15 ATK&DEF for each other exposed Nature card on your side | J19: Yes | K19: =(D19*6)+(E19*4) -> 450 | L19: Yes | N19: Yes
A20: Ironclad Sentinel | B20: Unit | C20: 1100 | D20: 55 | E20: 95 | F20: Anima | G20: 5 | H20: Immune to 0-cost Traps. This Unit cannot be destroyed by Tech Cards. | J20: Yes | K20: =(D20*6)+(E20*4) -> 710
A21: Tomb Bandit | B21: Unit | C21: 1000 | D21: 75 | E21: 60 | F21: Anima | G21: 4 | H21: This Unit cannot be destroyed by Traps. It gets -20 DEF permanently if it attacked a trap card. | J21: Yes | K21: =(D21*6)+(E21*4) -> 690 | L21: Yes | P21: Yes
A22: Scout Probe | B22: Unit | C22: 700 | D22: 40 | E22: 50 | F22: Cosmic | G22: 3 | H22: After this card attacks, choose and reveal 1 adjacent cell. | J22: Yes | K22: =(D22*6)+(E22*4) -> 440 | L22: Yes | N22: Yes
A23: Lab Zombie | B23: Unit | C23: 700 | D23: 55 | E23: 20 | F23: Bio | G23: 3 | H23: With Mutagen Flag: +45 ATK vs Nature or Anima. | J23: Yes | K23: =(D23*6)+(E23*4) -> 410 | L23: Yes | O23: Yes
A24: Lab Bloater | B24: Unit | C24: 800 | D24: 20 | E24: 85 | F24: Bio | G24: 4 | H24: With Mutagen Flag: Destroy both units in Reckoning. Both players pay no cost. | J24: Yes | K24: =(D24*6)+(E24*4) -> 460 | L24: Yes | P24: Yes
A25: Lab Crawler | B25: Unit | C25: 1200 | D25: 95 | E25: 60 | F25: Bio | G25: 5 | H25: With Mutagen Flag: this card can target 3 cards | J25: Yes | K25: =(D25*6)+(E25*4) -> 810 | L25: Yes | N25: Yes
A26: Pit Lord | B26: Unit | C26: 1250 | D26: 120 | E26: 100 | F26: Chaos | G26: 5 | H26: Destroy this card after Reckoning with Divine Unit. After this card attacked, halve its ATK&DEF permanently | J26: Yes | K26: =(D26*6)+(E26*4) -> 1120 | L26: Yes | O26: Yes
A27: Ancient Lich | B27: Unit | C27: 750 | D27: 60 | E27: 60 | F27: Chaos | G27: 3 | H27: This card is unaffected by Tech cards. | J27: Yes | K27: =(D27*6)+(E27*4) -> 600
A28: Hyperspeed Saucer | B28: Unit | C28: 850 | D28: 80 | E28: 40 | F28: Cosmic | G28: 4 | H28: Permanently increase this card's ATK&DEF by 10 at the end of each of your turn | J28: Yes | K28: =(D28*6)+(E28*4) -> 640
A29: Mountain Sage | B29: Unit | C29: 600 | D29: 50 | E29: 30 | F29: Arcane | G29: 3 | H29: Double effect of Tech card applied to this unit | J29: Yes | K29: =(D29*6)+(E29*4) -> 420
A30: War Genie | B30: Unit | C30: 1150 | D30: 100 | E30: 80 | F30: Arcane | G30: 4 | H30: -10 ATK permanently after it attacked | J30: Yes | K30: =(D30*6)+(E30*4) -> 920 | L30: Yes | P30: Yes
A31: Grand Wizard | B31: Unit | C31: 1100 | D31: 90 | E31: 70 | F31: Arcane | G31: 4 | H31: In Reckoning, flip a coin. Head: +30 ATK&DEF until this turn’s end | J31: Yes | K31: =(D31*6)+(E31*4) -> 820
A32: Archbishop | B32: Unit | C32: 1200 | D32: 70 | E32: 90 | F32: Divine | G32: 4 | H32: If this card would be destroyed, you can destroy 1 other Divine card on your side instead | J32: Yes | K32: =(D32*6)+(E32*4) -> 780 | L32: Yes | P32: Yes
A33: Space Boy | B33: Unit | C33: 800 | D33: 75 | E33: 65 | F33: Cosmic | G33: 3 | H33: None | J33: Yes | K33: =(D33*6)+(E33*4) -> 710 | L33: Yes | O33: Yes
A34: Slim Gray Trooper | B34: Unit | C34: 800 | D34: 45 | E34: 45 | F34: Cosmic | G34: 2 | H34: +65 ATK&DEF if 10 or more cells on your side are revealed | J34: Yes | K34: =(D34*6)+(E34*4) -> 450
A35: Horn Face | B35: Unit | C35: 1350 | D35: 85 | E35: 60 | F35: Cosmic | G35: 5 | H35: After a successful attack, flip 2 coins. It can attack again equal to number of head. | J35: Yes | K35: =(D35*6)+(E35*4) -> 750
A36: Railgun Tank | B36: Unit | C36: 1500 | D36: 150 | E36: 95 | F36: Anima | G36: 5 | H36: After a successful attack, this card cannot attack on the next of your turn. | J36: Yes | K36: =(D36*6)+(E36*4) -> 1280 | L36: Yes
A37: Lazy Troll | B37: Unit | C37: 1000 | D37: 120 | E37: 60 | F37: Nature | G37: 5 | H37: If this card performs an attack, flip a coin. Tail: it stops attacking. | J37: Yes | K37: =(D37*6)+(E37*4) -> 960 | L37: Yes | N37: Yes
A38: Leech Man | B38: Unit | C38: 880 | D38: 60 | E38: 40 | F38: Bio | G38: 4 | H38: +10 DEF permanently after it performed attack on unit. Also +10 ATK with mutagen flag | J38: Yes | K38: =(D38*6)+(E38*4) -> 520 | L38: Yes | O38: Yes
A39: Immortal Vampire | B39: Unit | C39: 1200 | D39: 30 | E39: 80 | F39: Chaos | G39: 4 | H39: +30 ATK for each other exposed Chaos card on your side. In Reckoning with Divine, destroy this card. | J39: Yes | K39: =(D39*6)+(E39*4) -> 500 | L39: Yes | N39: Yes
A40: Vampire Servant | B40: Unit | C40: 800 | D40: 20 | E40: 20 | F40: Chaos | G40: 2 | H40: If a 'Vampire' card will be destroyed, destroy this card instead. Usable face-down. | J40: Yes | K40: =(D40*6)+(E40*4) -> 200 | L40: Yes | O40: Yes
A41: Bat Swarm | B41: Unit | C41: 200 | D41: 15 | E41: 15 | F41: Chaos | G41: 3 | H41: If a Chaos card on your side is being attacked, you may swap this card's position with that card. Usable face-down. | J41: Yes | K41: =(D41*6)+(E41*4) -> 150 | L41: Yes | N41: Yes
A42: Poltergeist | B42: Unit | C42: 700 | D42: 0 | E42: 70 | F42: Chaos | G42: 3 | H42: If this card performs an attack, switch this card’s ATK&DEF | J42: Yes | K42: =(D42*6)+(E42*4) -> 280 | L42: Yes | N42: Yes
A43: Giant Mosquito | B43: Unit | C43: 800 | D43: 30 | E43: 20 | F43: Nature | G43: 5 | H43: If this card performs an attack, +ATK equal to half of target’s ATK until the end of this turn | J43: Yes | K43: =(D43*6)+(E43*4) -> 260
A44: Street Rogue | B44: Unit | C44: 350 | D44: 25 | E44: 20 | F44: Anima | G44: 1 | H44: +20 ATK against Anima card | J44: Yes | K44: =(D44*6)+(E44*4) -> 230 | L44: Yes | N44: Yes
A45: Big Thug | B45: Unit | C45: 400 | D45: 40 | E45: 35 | F45: Anima | G45: 2 | H45: None | J45: Yes | K45: =(D45*6)+(E45*4) -> 380 | L45: Yes
A46: Goblin Poacher | B46: Unit | C46: 250 | D46: 30 | E46: 10 | F46: Nature | G46: 1 | H46: None | J46: Yes | K46: =(D46*6)+(E46*4) -> 220 | L46: Yes | P46: Yes
A47: Ectoplasm | B47: Unit | C47: 800 | D47: 20 | E47: 0 | F47: Bio | G47: 5 | H47: After this card is destroyed in Reckoning, revive 1 unit you own with no ability. Repeat the Reckoning. | J47: Yes | K47: =(D47*6)+(E47*4) -> 120
A48: Death Stag | B48: Unit | C48: 400 | D48: 45 | E48: 30 | F48: Nature | G48: 2 | H48: None | J48: Yes | K48: =(D48*6)+(E48*4) -> 390
A49: Champion of the Valley | B49: Unit | C49: 400 | D49: 35 | E49: 45 | F49: Anima | G49: 2 | H49: +10 ATK permanently if it destroyed a unit. This bonus does not exceed 30 | J49: Yes | K49: =(D49*6)+(E49*4) -> 390
A50: Magenta the Nightbloom | B50: Unit | C50: 300 | D50: 25 | E50: 40 | F50: Chaos | G50: 1 | H50: Half its DEF permanently at the end of that turn | J50: Yes | K50: =(D50*6)+(E50*4) -> 310 | L50: Yes | N50: Yes
A51: Jirayu the Rebellious Prince | B51: Unit | C51: 600 | D51: 40 | E51: 40 | F51: Anima | G51: 2 | H51: If this card successfully defended, +10 DEF permanently | J51: Yes | K51: =(D51*6)+(E51*4) -> 400 | L51: Yes | O51: Yes
A52: Ice Mage | B52: Unit | C52: 400 | D52: 50 | E52: 0 | F52: Arcane | G52: 2 | H52: None | J52: Yes | K52: =(D52*6)+(E52*4) -> 300 | L52: Yes | P52: Yes
A53: Star Hunter | B53: Unit | C53: 250 | D53: 30 | E53: 10 | F53: Cosmic | G53: 1 | H53: None | J53: Yes | K53: =(D53*6)+(E53*4) -> 220
A54: Slim Gray Tank | B54: Unit | C54: 1000 | D54: 30 | E54: 30 | F54: Cosmic | G54: 5 | H54: +10 ATK/DEF per revealed cell on your side | J54: Yes | K54: =(D54*6)+(E54*4) -> 300 | L54: Yes
A55: Mafia Associates | B55: Unit | C55: 500 | D55: 45 | E55: 40 | F55: Anima | G55: 2 | H55: At the end of the turn that it’s been exposed, its defense becomes 0 | J55: Yes | K55: =(D55*6)+(E55*4) -> 430 | L55: Yes | P55: Yes
A56: Silver Dragon | B56: Unit | C56: 1500 | D56: 155 | E56: 95 | F56: Arcane | G56: 5 | H56: Pay 1000 Crystal tax to command this card for attack | J56: Yes | K56: =(D56*6)+(E56*4) -> 1310 | L56: Yes
A57: Energy Wisp | B57: Unit | C57: 100 | D57: 20 | E57: 10 | F57: Arcane | G57: 3 | H57: None | J57: Yes | K57: =(D57*6)+(E57*4) -> 160
A58: Wood Wisp | B58: Unit | C58: 100 | D58: 10 | E58: 20 | F58: Nature | G58: 3 | H58: None | J58: Yes | K58: =(D58*6)+(E58*4) -> 140
A59: Messenger of Fate | B59: Unit | C59: 500 | D59: 45 | E59: 35 | F59: Divine | G59: 2 | H59: In Reckoning, flip a coin. Head: +20 ATK&DEF. Tail -20 ATK&DEF | J59: Yes | K59: =(D59*6)+(E59*4) -> 410
A60: Armored Wolf | B60: Unit | C60: 800 | D60: 40 | E60: 80 | F60: Nature | G60: 3 | H60: Once in Reckoning, you can choose to grant +50 ATK and -50 DEF to it permanently | J60: Yes | K60: =(D60*6)+(E60*4) -> 560
A61: Berserker of Ice Sea | B61: Unit | C61: 1000 | D61: 105 | E61: 50 | F61: Anima | G61: 3 | H61: Once, at your turn end, -35 ATK | J61: Yes | K61: =(D61*6)+(E61*4) -> 830 | L61: Yes
A62: Armored Elephant | B62: Unit | C62: 800 | D62: 20 | E62: 150 | F62: Nature | G62: 5 | H62: -50 DEF for each successful defense | J62: Yes | K62: =(D62*6)+(E62*4) -> 720
A63: Battle Penguin | B63: Unit | C63: 300 | D63: 20 | E63: 15 | F63: Nature | G63: 1 | H63: +15 ATK until the end of that turn, once. | J63: Yes | K63: =(D63*6)+(E63*4) -> 180
A64: Star Crusader | B64: Unit | C64: 250 | D64: 25 | E64: 25 | F64: Divine | G64: 1 | H64: None | J64: Yes | K64: =(D64*6)+(E64*4) -> 250
A65: Gryphon | B65: Unit | C65: 1150 | D65: 100 | E65: 85 | F65: Nature | G65: 5 | H65: None | J65: Yes | K65: =(D65*6)+(E65*4) -> 940 | L65: Yes | O65: Yes
A66: Cleaver Saint | B66: Unit | C66: 1200 | D66: 95 | E66: 80 | F66: DIvine | G66: 4 | H66: None | J66: Yes | K66: =(D66*6)+(E66*4) -> 890
A67: Succubus | B67: Unit | C67: 600 | D67: 10 | E67: 30 | F67: Chaos | G67: 1 | H67: Once, if survived Reckoning: +ATK&DEF equal to half of that foe’s card | J67: Yes | K67: =(D67*6)+(E67*4) -> 180 | L67: Yes | O67: Yes
A68: Wide Smile Lady | B68: Unit | C68: 200 | D68: 25 | E68: 0 | F68: Chaos | G68: 1 | H68: None | J68: Yes | K68: =(D68*6)+(E68*4) -> 150
A69: Nuki the Tanuki | B69: Unit | C69: 100 | D69: 10 | E69: 10 | F69: Nature | G69: 1 | H69: Before Reckoning, flip a coin. If head, swap position with any of own unit. Repeat Reckoning. | J69: Yes | K69: =(D69*6)+(E69*4) -> 100 | L69: Yes | P69: Yes
A70: Tiny Pixie | B70: Unit | C70: 100 | D70: 0 | E70: 0 | F70: Divine | G70: 1 | H70: Once, this card is not destroyed | J70: Yes | K70: =(D70*6)+(E70*4) -> 0 | L70: Yes | N70: Yes
A71: Melissa the Healer | B71: Unit | C71: 700 | D71: 0 | E71: 25 | F71: Divine | G71: 1 | H71: If you lose 500 or more Crystals, you recover 300 Crystals. | J71: Yes | K71: =(D71*6)+(E71*4) -> 100 | L71: Yes | N71: Yes
A72: Heavy Tome Preacher | B72: Unit | C72: 300 | D72: 25 | E72: 20 | F72: Divine | G72: 1 | H72: None | J72: Yes | K72: =(D72*6)+(E72*4) -> 230 | L72: Yes | P72: Yes
A73: Holy Wisp | B73: Unit | C73: 200 | D73: 10 | E73: 20 | F73: Divine | G73: 1 | H73: +10 ATK vs Chaos | J73: Yes | K73: =(D73*6)+(E73*4) -> 140
A74: Cloud Soldier | B74: Unit | C74: 200 | D74: 20 | E74: 15 | F74: Divine | G74: 1 | H74: None | J74: Yes | K74: =(D74*6)+(E74*4) -> 180
A75: Sleeping Kirin | B75: Unit | C75: 400 | D75: 0 | E75: 25 | F75: Divine | G75: 1 | H75: +25 ATK permanently | J75: Yes | K75: =(D75*6)+(E75*4) -> 100
A76: Ponycorn | B76: Unit | C76: 300 | D76: 25 | E76: 20 | F76: Divine | G76: 2 | H76: None | J76: Yes | K76: =(D76*6)+(E76*4) -> 230 | L76: Yes
A77: Nunchuck Nun | B77: Unit | C77: 320 | D77: 25 | E77: 15 | F77: Divine | G77: 1 | H77: + 5 ATK&DEF vs Chaos card | J77: Yes | K77: =(D77*6)+(E77*4) -> 210
A78: Joan the Faithful Warrior | B78: Unit | C78: 280 | D78: 25 | E78: 5 | F78: Divine | G78: 1 | H78: If at least 1 exposed Divine unit is on the field, this card gains 35 DEF | J78: Yes | K78: =(D78*6)+(E78*4) -> 170 | L78: Yes | O78: Yes
A79: Choir Lady Alice | B79: Unit | C79: 250 | D79: 20 | E79: 25 | F79: Divine | G79: 1 | H79: None | J79: Yes | K79: =(D79*6)+(E79*4) -> 220 | L79: Yes
A80: Choir Lady Anna | B80: Unit | C80: 250 | D80: 20 | E80: 20 | F80: Divine | G80: 1 | H80: None | J80: Yes | K80: =(D80*6)+(E80*4) -> 200 | L80: Yes
A81: Choir Lady Abigail | B81: Unit | C81: 250 | D81: 25 | E81: 15 | F81: Divine | G81: 1 | H81: None | J81: Yes | K81: =(D81*6)+(E81*4) -> 210 | L81: Yes
A82: Church Guard | B82: Unit | C82: 150 | D82: 0 | E82: 35 | F82: Divine | G82: 1 | H82: None | J82: Yes | K82: =(D82*6)+(E82*4) -> 140 | L82: Yes | P82: Yes
A83: Sniping Fairy | B83: Unit | C83: 350 | D83: 40 | E83: 20 | F83: Divine | G83: 2 | H83: After it becomes exposed, -20 ATK at that turn’s end. | J83: Yes | K83: =(D83*6)+(E83*4) -> 320 | L83: Yes | N83: Yes
A84: Bomber Fairy | B84: Unit | C84: 500 | D84: 30 | E84: 15 | F84: Divine | G84: 2 | H84: Once, after destroyed a unit, this card can attack 1 more time. | J84: Yes | K84: =(D84*6)+(E84*4) -> 240 | L84: Yes | N84: Yes
A85: Totem Granpa | B85: Unit | C85: 420 | D85: 20 | E85: 20 | F85: Divine | G85: 2 | H85: +30 DEF vs Nature | J85: Yes | K85: =(D85*6)+(E85*4) -> 200
A86: Golden Senju | B86: Unit | C86: 200 | D86: 15 | E86: 0 | F86: Divine | G86: 2 | H86: After attacked a non-unit cell, this card can attack 1 more time. | J86: Yes | K86: =(D86*6)+(E86*4) -> 90 | L86: Yes
A87: Mean Angel | B87: Unit | C87: 250 | D87: 20 | E87: 10 | F87: Divine | G87: 1 | H87: Once, destroy Anima card in Reckoning | J87: Yes | K87: =(D87*6)+(E87*4) -> 160
A88: Sandy Sphinx | B88: Unit | C88: 450 | D88: 20 | E88: 20 | F88: Divine | G88: 1 | H88: In Reckoning if it defends, flip a coin. Head: the attack does nothing. | J88: Yes | K88: =(D88*6)+(E88*4) -> 200
A89: Gemmed Sphinx | B89: Unit | C89: 700 | D89: 40 | E89: 40 | F89: Divine | G89: 2 | H89: In Reckoning if it defends, flip a coin. Head: the attack does nothing. | J89: Yes | K89: =(D89*6)+(E89*4) -> 400
A90: Black Anubis | B90: Unit | C90: 1100 | D90: 75 | E90: 90 | F90: Divine | G90: 4 | H90: +5 ATK at your turn end. This bonus does not exceed 25 | J90: Yes | K90: =(D90*6)+(E90*4) -> 810
A91: Sunrise Lady | B91: Unit | C91: 300 | D91: 20 | E91: 30 | F91: Divine | G91: 1 | H91: If it attacks: +10 ATK,-10 DEF permanently (if possible) | J91: Yes | K91: =(D91*6)+(E91*4) -> 240 | L91: Yes | P91: Yes
A92: Lucky Statue | B92: Unit | C92: 400 | D92: 40 | E92: 30 | F92: Divine | G92: 2 | H92: +20 DEF vs Chaos | J92: Yes | K92: =(D92*6)+(E92*4) -> 360
A93: Flame Seraph | B93: Unit | C93: 500 | D93: 50 | E93: 10 | F93: Divine | G93: 2 | H93: None | J93: Yes | K93: =(D93*6)+(E93*4) -> 340 | L93: Yes | O93: Yes
A94: Halo Guardian | B94: Unit | C94: 450 | D94: 35 | E94: 35 | F94: Divine | G94: 2 | H94: +5 ATK&DEF for each exposed Chaos unit on foe’s side | J94: Yes | K94: =(D94*6)+(E94*4) -> 350
A95: Benjamin the Holy Craftsman | B95: Unit | C95: 300 | D95: 25 | E95: 30 | F95: Divine | G95: 2 | H95: +10 ATK&DEF to other Divine card on your side | J95: Yes | K95: =(D95*6)+(E95*4) -> 270
A96: Raijin | B96: Unit | C96: 550 | D96: 60 | E96: 0 | F96: Divine | G96: 3 | H96: None | J96: Yes | K96: =(D96*6)+(E96*4) -> 360 | L96: Yes | N96: Yes
A97: Moonrise Gentleman | B97: Unit | C97: 400 | D97: 40 | E97: 30 | F97: Divine | G97: 2 | H97: If it defends: +10 DEF,-10 ATK permanently (if possible) | J97: Yes | K97: =(D97*6)+(E97*4) -> 360 | L97: Yes | P97: Yes
A98: Fujin | B98: Unit | C98: 450 | D98: 35 | E98: 40 | F98: Divine | G98: 2 | H98: None | J98: Yes | K98: =(D98*6)+(E98*4) -> 370 | L98: Yes | N98: Yes
A99: Jiro the Battlemaster | B99: Unit | C99: 500 | D99: 65 | E99: 30 | F99: Divine | G99: 3 | H99: -10 ATK permanently at the end of that turn if this card has not performed attack. | J99: Yes | K99: =(D99*6)+(E99*4) -> 510
A100: Angel Mauler | B100: Unit | C100: 700 | D100: 45 | E100: 40 | F100: Divine | G100: 2 | H100: This card is not destroyed by Chaos cards | J100: Yes | K100: =(D100*6)+(E100*4) -> 430
...

Sheet Union
A1: Table 1
A2: Card Name | B2: Union | C2: Cost | D2: ATK | E2: DEF | F2: Affinity | G2: Rarity | H2: Partial Ability | I2: Full Ability | J2: Partial Formula | K2: Full Formula | L2: Union Zone | M2: Have illustration | N2: Demo | O2: Test 1
A3: Gryphon Rider | B3: Union | D3: 125 | E3: 90 | F3: Divine | H3: None | I3: None | J3: 1 ??? + 1 ??? + 1000 cost | K3: Gryphon + 1 Divine + 1000 cost | L3: 10000 01000 00100 00010 00001 | M3: Yes | N3: Yes
A4: Seraphim Fistmaster | B4: Union | D4: 120 | E4: 120 | F4: Divine | H4: Double ATK&DEF against ??? Affinity | I4: Double ATK&DEF against Chaos | J4: 1 ??? + 1 ??? + 1500 cost | K4: 1 ‘Seraph’ unit + 1 Divine (≥ 800 cost) + 1500 cost | L4: 11011 10001 00000 10001 11011 | M4: Yes | N4: Yes
A5: Gaia Turtle | B5: Union | D5: 0 | E5: 210 | F5: Nature | H5: None | I5: None | J5: 2 ??? + 2000 cost | K5: 2 any units (≥90 DEF) + 2000 cost | L5: 00000 00000 01110 01110 00000 | M5: Yes | N5: Yes
A6: Barros the Colossal | B6: Union | D6: 150 | E6: 130 | F6: Nature | H6: None | I6: None | J6: 2 ???+ 1500 cost | K6: 2 Nature (≥ 800 cost) + 1500 cost | L6: 00000 01010 00100 01010 00000 | M6: Yes | N6: Yes
A7: X-Death Squad | B7: Union | D7: 50 | E7: 50 | F7: Anima | H7: In Reckoning, pay ???, destroy foe’s unit. They pay ???. | I7: In Reckoning, pay 1000, destroy foe’s unit. They pay no cost. | J7: 1 ??? + 2 ??? + 800 cost | K7: 1 Anima (≥ 800 cost) + 2 Anima + 800 cost | L7: 10101 00000 10101 00000 10101 | M7: Yes | N7: Yes
A8: Rocket Marauder | B8: Union | D8: 125 | E8: 105 | F8: Bio | H8: None | I8: None | J8: 1 ??? + 1 ??? + 1000 cost | K8: 1 Bio (≥ 800 cost) + 1 Anima (≥ 800 cost) + 1000 cost | L8: 00000 00000 00000 01010 10101 | M8: Yes | N8: Yes
A9: Lord of Terror | B9: Union | D9: 150 | E9: 100 | F9: Chaos | H9: -50 ATK if ??? | I9: -50 ATK if attacks Dead End | J9: 2 ??? + 1500 cost | K9: 2 Chaos (≥ 800 cost) + 1500 cost | L9: 00000 00100 00100 01110 00100 | M9: Yes | N9: Yes
A10: Armored Dino | B10: Union | D10: 95 | E10: 60 | F10: Nature | H10: In Reckoning, pay ??? Crystal cost to +??DEF | I10: In Reckoning, pay 1000 Crystal cost to +60 DEF | J10: 1 ??? + 1 ??? + 700 cost | K10: 1 Armored Nature card + 1 Nature (≥ 700 cost) + 800 cost | L10: 00000 01110 11111 00000 00000 | M10: Yes | N10: Yes
A11: Greater Succubus | B11: Union | D11: 30 | E11: 50 | F11: Chaos | H11: Once, after Reckoning: +ATK&DEF equal to ??? | I11: Once, after Reckoning: +ATK&DEF equal to half of that foe’s card | J11: 1 ??? + 1 ??? + 800 cost | K11: 1 Succubus + 1 Chaos + 800 cost | L11: 00100 11111 10001 00000 00000 | M11: Yes | N11: Yes
A12: Pixie Queen | B12: Union | D12: 30 | E12: 30 | F12: Divine | H12: +5 ATK for each ???? | I12: +5 ATK for each Divine cards on your side | J12: 1 ??? + 1 ??? + 300 cost | K12: 1 Tiny Pixie + 1 Divine+ 300 cost | L12: 00100 00100 10001 10101 01010 | M12: Yes | N12: Yes
A13: Diamond Unicorn | B13: Union | D13: 30 | E13: 35 | F13: Divine | H13: Summoned: ??? until this turn’s end | I13: Summoned: +15 ATK until this turn’s end | J13: 1 ??? + 1 ??? + 500 cost | K13: 1 Ponycorn + 1 Divine card + 500 cost | L13: 00100 01010 10001 01010 00100 | M13: Yes | N13: Yes
A14: Choir Lead Amber | B14: Union | D14: 35 | E14: 35 | F14: Divine | H14: +20 ATK to all ????? | I14: +20 ATK to all Divine units on your side | J14: 3 ??? + 500 cost | K14: 3 Choir Lady cards + 500 cost | L14: 01100 01011 01001 11000 11000 | M14: Yes | N14: Yes
... A36: Giant Meteor Vergaia | B36: Union | D36: 60 | E36: 0 | F36: Cosmic | H36: Destroy it at turn's end, then destroy all ??? | I36: Destroy it at turn's end, then destroy all exposed foe’s units surrounding the card that this card attacked. | J36: ??? + ??? + 1000 cost | K36: Striker Comet + 2 Cosmic card + 1000 cost | L36: 10000 01000 00000 00111 00111 | M36: Yes | N36: Yes
A37: Blood-hungry Mutant | B37: Union | D37: 55 | E37: 40 | F37: Bio | H37: After destroying foe’s card: ??? | I37: After destroying foe’s card: +80 Crystals | J37: 2 ??? + 600 cost | K37: 2 Mutant cards + 600 cost | L37: 00000 01010 10101 01010 00000 | M37: Yes
A38: Gamma Mermaid | B38: Union | D38: 30 | E38: 20 | F38: Bio | H38: Non-Bio defender get ???. With Mutagen Flag: +20 ??? | I38: Non-Bio defender get -20 DEF. With Mutagen Flag: +20 ATK&DEF to all ally Bio units | J38: ??? + ??? + 1000 cost | K38: 1 Gamma cards + 1 Bio card + 500 cost | L38: 00000 01110 01010 01110 00000 | M38: Yes | N38: Yes
A39: Tendrill Tyrant | B39: Union | D39: 90 | E39: 110 | F39: Bio | H39: Can attack ? times per turn | I39: Can attack 3 times per turn | J39: 1 ??? + 2 ??? + 1500 cost | K39: 1 Bio with mutagen flag + 2 Bio (≥ 800 cost) + 1500 cost | L39: 00100 00100 11111 00100 00100
A40: Helios the Prideful Fortress | B40: Union | D40: 145 | E40: 60 | F40: Cosmic | H40: As long as there is exposed ???, this card cannot be ???. If targeted by tech, ??? | I40: With another exposed Cosmic: this card cannot be destroyed. If targeted by tech, destroy this card. | J40: 2 ??? + 1500 cost | K40: 2 Cosmic (≥ 800 cost) + 1500 cost | L40: 00100 01010 10001 01010 00100 | M40: Yes | N40: Yes
A41: Slim Gray Plasma Bomber | B41: Union | D41: 80 | E41: 60 | F41: Cosmic | H41: +?? ATK&DEF if ?? or more of cells on your side are revealed | I41: +100 ATK&DEF if 10 or more cells on your side are revealed | J41: 1 ??? + 1 ??? + 1000 cost | K41: 1 Slim Gray + 1 Cosmic (≥ 800 cost) + 1000 cost | L41: 00100 01110 01010 01110 00000
A42: Interplanetary Assassin | B42: Union | D42: 50 | E42: 70 | F42: Cosmic | H42: +?? ATK vs Cosmic | I42: +100 ATK vs Cosmic | J42: 1 ??? + 1 ??? + 1500 cost | K42: 1 Cosmic (≥ 500 cost) + 1 Cosmic + 1500 cost | L42: 00100 11111 00000 11111 00100
A43: Bioterrorist | B43: Union | D43: 150 | E43: 0 | F43: Bio | H43: Destroy this card after ??? | I43: Destroy this card after Reckoning | J43: 2 ??? + 1000 cost | K43: 2 Bio cards (≥ 800 cost) + 1000 cost | L43: 10001 01010 00000 01010 10001 | M43: Yes | N43: Yes
A44: One Winged Angel | B44: Union | D44: 120 | E44: 120 | F44: Divine | H44: +??? ATK permanently at ??? | I44: +30 ATK permanently at the end of your turn (max 120) | J44: 1 ??? + 1 ??? + 1500 cost | K44: 1 Cleaver Saint + 1 Divine card + 1500 cost | L44: 00011 00011 00011 00011 00011
A45: Genesis Mech | B45: Union | D45: 60 | E45: 40 | F45: Divine | H45: Once, destroy ???or ??? card | I45: Once, destroy Divine or Anima card | J45: 1 ??? + 1 ??? + 1000 cost | K45: 1 Mean Angel + 1 Anima Card + 1000 cost | L45: 11111 11111 00000 00000 00000
A46: Keeper of the Afterlife | B46: Union | D46: 40 | E46: 65 | F46: Divine | H46: At Reckoning, flip a coin. If head, ???? | I46: At Reckoning, flip a coin. If head, the attack does nothing | J46: 1 ??? + 1 ???+ 1000 cost | K46: 1 Sphinx unit + 1 Divine card + 1000 cost | L46: 00000 00000 00100 01110 11111
A47: Keeper of the Sun | B47: Union | D47: 70 | E47: 35 | F47: Divine | H47: This card cannot attack if there is card with affinity other than ??? Or ??? | I47: This card cannot attack if there is card with affinity other than Divine or Anima on your side | J47: 1 ???+ ??? + 1000 cost | K47: 1 Sphinx unit + 1 Anima + 1000 cost | L47: 11111 01110 00100 00000 00000
A48: Keeper of Righteous | B48: Union | D48: 90 | E48: 80 | F48: Divine | H48: +??? ATK vs ?? and ?? | I48: +20 ATK vs Chaos and Arcane | J48: 2 ???+ 1000 cost | K48: 2 Sphinx units + 1000 cost | L48: 10001 01010 00100 01010 10001
A49: Lucky Wanderer | B49: Union | D49: 70 | E49: 50 | F49: Divine | H49: During the end of that turn, flip a coin. If head, +??? ATK. If tail, +?? DEF | I49: During the end of that turn, flip a coin. If head, +10 ATK. If tail, +10 DEF | J49: 1 ??? + 1 ??? + 1000 cost | K49: 1 Lucky Statue + 1 Divine card + 1000 cost | L49: 00100 00100 00100 00100 00100
A50: Joyce the Rafflesia | B50: Union | D50: 45 | E50: 45 | F50: Divine | H50: At the end of this turn, +??? ATK&DEF ???? | I50: At the end of this turn, +5 ATK&DEF permanently. | J50: 1 ??? + 1 ??? + 1000 cost | K50: Bloom Fairy + 1 Nature card + 1000 cost | L50: 11111 11011 00100 00100 00100
A51: Twin Axe Saintess | B51: Union | D51: 40 | E51: 30 | F51: Divine | H51: This card can ??? per turn | I51: This card can attack twice per turn | J51: 1??? + 1 ??? + 1000 cost | K51: Lady of the Sacred Pond + 1 Anima + 600 cost | L51: 11011 01010 01010 01010 00000
A52: Blast Beam Seraph | B52: Union | D52: 100 | E52: 50 | F52: Divine | H52: None | I52: None | J52: 1 ??? + 1 ??? + 1000 cost | K52: Gerald of the Heavenly Light + 1 Divine + 1000 cost | L52: 11111 00100 11111 00100 00000
A53: Balthier the Supreme Holiness | B53: Union | D53: 100 | E53: 100 | F53: Divine | H53: +??? ATK&DEF for each ???cards on the field. | I53: +50 ATK&DEF for each Divine cards on the field. | J53: 2 ??? + 1500 cost | K53: 3 Divine (≥800 cost) + 1500 cost | L53: 00100 11111 00100 00100 00100
A54: Oblivion Dragon | B54: Union | D54: 200 | E54: 0 | F54: Chaos | H54: When this card defends, halve its ??? an??? | I54: When this card defends, halve its attack and gain DEF by that amount permanently | J54: 4 ??? + 2000 cost | K54: 4 Chaos card (≥500 cost) + 2000 cost | L54: 10001 00100 01010 00000 10001
A55: Big Bang Dragon | B55: Union | D55: 250 | E55: 180 | F55: Nature | H55: Summoned: destroy all ??? | I55: Summoned: destroy all other exposed ally units. No paid cost. | J55: 5 ??? + 2500 cost | K55: 5 Cosmic cards + 2500 cost | L55: 00001 00010 00100 01000 10000
... A64: Cullan the Flaming Blade | B64: Union | D64: 40 | E64: 30 | F64: Arcane | H64: +??? ATK&DEF vs Nature | I64: +30 ATK&DEF vs Nature | J64: 1 ??? + 1 ??? + 1000 cost | K64: Cullan the Magic Swordsman + Red Mage + 1000 cost | L64: 00001 00010 01100 01110 10000
A65: The Undertaker | B65: Union | D65: 90 | E65: 75 | F65: Chaos | H65: If foe destroys a card on your side, gain ??? | I65: If foe destroys a card on your side, gain +15 ATK permanently (max 90). | K65: Sinister Cultist + 1 Chaos card + 1000 cost | L65: 00000 00000 01110 01110 01110
A66: Ethereal Marquees | B66: Union | D66: 195 | E66: 180 | F66: Arcane | H66: -80 DEF if ??? | I66: -80 DEF vs Arcane card. If this survived Reckoning, pay 500 cost | K66: Nobleman card + Ethereal card + 1500 cost | L66: 00100 01010 10101 01010 10101
A67: Charm Mistress | B67: Union | D67: 30 | E67: 50 | F67: Arcane | H67: Foe’s turn start: flip a coin. Head, ??? | I67: Foe’s turn start: flip a coin. Head, foe can only attack once. | K67: Alluring Spellcaster + 1 Arcane + 1000 cost | L67: 00000 01010 01110 00100 00000
A68: Chronomancer | B68: Union | D68: 60 | E68: 80 | F68: Arcane | H68: For cannot revive or create token copy a unit. Once, after Arcane unit is destroyed, ??? | I68: For cannot revive or create token copy a unit. Once, after Arcane unit is destroyed, revive it. | K68: Freya the Rift Walker + Bingo the Chrono Rabbit + 1000 cost. | L68: 00010 01000 00010 01000 00001
A69: Death Colony | B69: Union | D69: 225 | E69: 150 | F69: Bio | H69: This card can only choose attack target in the same pattern as ??? | I69: This card can only choose attack target in the same pattern as its union zone | K69: Long Tongue + 1 Bio card + 1500 cost. | L69: 10001 01010 00100 01010 10001
A70: Diamond Elemental | B70: Union | D70: 60 | E70: 100 | F70: Arcane | H70: None | I70: None | J70: ??? + ??? + 1000 cost | K70: Fire Elemental + Earth Elemental + 1000 cost | L70: 01010 01110 01110 00100 00000 | M70: Yes | N70: Yes
A71: Ice Elemental | B71: Union | D71: 80 | E71: 50 | F71: Arcane | H71: Card that battles this card cannot ??? until the end of their next turn. | I71: Card that battles this card cannot perform attack until the end of their next turn. | J71: ??? + ??? + 1000 cost | K71: Water Elemental + Wind Elemental + 1000 cost | L71: 00000 01110 00100 01110 00000 | M71: Yes | N71: Yes
A72: Cloud Elemental | B72: Union | D72: 65 | E72: 65 | F72: Arcane | H72: Once, this card is ??? | I72: Once, this card is not destroyed | J72: ??? + ??? + 1000 cost | K72: Fire Elemental + Water Elemental + 1000 cost | L72: 00100 00100 01110 01110 00000 | M72: Yes | N72: Yes
A73: Thunder Elemental | B73: Union | D73: 90 | E73: 55 | F73: Arcane | H73: After a successful attack, ??? | I73: After a successful attack, reveal 1 foe’s card | J73: ??? + ??? + 1000 cost | K73: Fire Elemental + Wind Elemental + 1000 cost | L73: 00010 00110 00100 01100 01000 | M73: Yes | N73: Yes
A74: Wood Elemental | B74: Union | D74: 65 | E74: 85 | F74: Arcane | H74: At the end of each foe’s turn, ??? | I74: At the end of each foe’s turn, +5 DEF permanently. | J74: ??? + ??? + 1000 cost | K74: Water Elemental + Earth Elemental + 1000 cost | L74: 00000 00000 01110 01110 01110 | M74: Yes | N74: Yes
A75: Sand Elemental | B75: Union | D75: 40 | E75: 40 | F75: Arcane | H75: +??? vs Non-Arcane cards | I75: +60 ATK&DEF vs Non-Arcane cards | J75: ??? + ??? + 1000 cost | K75: Wind Elemental + Earth Elemental + 1000 cost | L75: 00000 01110 01110 01110 00000 | M75: Yes | N75: Yes
A76: Nuclear Elemental | B76: Union | D76: 120 | E76: 80 | F76: Arcane | H76: At the end of this turn, ??? permanently | I76: At the end of this turn, +10 ATK permanently | K76: Mind Elemental + Fire Elemental + 1500 cost | L76: 00000 01110 01110 01110 00000
A77: Acid Elemental | B77: Union | D77: 50 | E77: 120 | F77: Arcane | H77: Summoned : put acid flag on ???. Card with acid flag get ??? | I77: Summoned : put acid flag on all of foe’s exposed card. Card with acid flag get -10 DEF at the end of foe’s turn | K77: Mind Elemental + Water Elemental + 1500 cost | L77: 00000 01110 01110 01110 00000
A78: Vacuum Elemental | B78: Union | D78: 175 | E78: 0 | F78: Arcane | H78: None | I78: None | K78: Mind Elemental + Wind Elemental + 1500 cost | L78: 00000 01110 01110 01110 00000
A79: Magnet Elemental | B79: Union | D79: 10 | E79: 135 | F79: Arcane | I79: Foe’s non-Arcane cards cannot target exposed card other than this card. | K79: Mind Elemental + Earth Elemental + 1500 cost | L79: 00000 01110 01110 01110 00000
A80: Dwarven Berserker | B80: Union | D80: 120 | E80: 0 | F80: Arcane | I80: This card can attack twice | K80: 1 Dwarven card + 1 Arcane or Anima card + 1500 cost | L80: 01110 10101 00100 00100 00000
A81: Tholin Whale | B81: Union | D81: 50 | E81: 200 | F81: Cosmic | I81: If attacked a trap, +100 ATK permanently | K81: 2 Tholin card + 1000 cost | L81: 11000 10000 01111 01111 00000
A82: Dark Invader | B82: Union | D82: 50 | E82: 30 | F82: Cosmic | I82: +5 ATK&DEF per revealed cells on your side | K82: Lukkey the Jammer+ 1 Cosmic card + 1000 cost | L82: 00000 01110 01010 11111 00000
A83: Europan Warcraft | B83: Union | D83: 85 | E83: 105 | F83: Cosmic | I83: If this card is going to be destroy, you can remove 1 Europa flag from any card on your side. | K83: 2 Europan cards + 1000 cost | L83: 00000 10000 10000 01111 01110
A84: Nanomites Dragon | B84: Union | D84: 125 | E84: 100 | F84: Bio | I84: Destroy Cosmic card in Reckoning | K84: 1 Nanomites cards + 1 Bio card + 1000 cost | L84: 10001 01010 01010 00100 10001
A85: Capnomancer | B85: Union | C85: 0 | D85: 0 | E85: 180 | F85: Arcane | H85: Start of your turn: can choose to destroy this card to ??? | I85: Start of your turn: can choose to destroy this card to revive Pyromancer | J85: 1 ??? | K85: 1 Pyromancer + 1 Cosmic + 500 cost | L85: 00000 01110 01110 01110 00000
A86: Immortal Siegfried | B86: Union | D86: 40 | E86: 60 | F86: Anima | H86: If there is Anima on this card’s Union Zone, ??? | I86: If there is Anima unit on this card’s Union Zone, this card is not destroyed | K86: 2 Anima (DEF ≥ 100) + 1000 cost | L86: 00000 01110 01010 01110 00000
A87: Dark Champion | B87: Union | D87: 170 | E87: 150 | F87: Chaos | H87: Cannot select unit with ??? target. Destroy ??? with 0 ATK unit | I87: Cannot select unit with 0 DEF as attack target. Destroy this card in Reckoning with 0 ATK unit | K87: 1 Death Knight + 1 Chaos card + 1000 cost | L87: 00001 00010 10100 01000 10100
A88: Legendary Locksmith | B88: Union | D88: 35 | E88: 60 | F88: Anima | H88: Summoned: Reveal ??? cards on the field | I88: Summoned: Reveal 3 cards on the field | J88: 1 ??? + 1 ??? + 800 cost | K88: 1 Lockpicker + 1 Anima + 800 cost | L88: 01100 00100 01100 00100 00100 | M88: Yes | N88: Yes
A89: Perseus the Lightborn | B89: Union | D89: 55 | E89: 40 | F89: Divine | H89: Summoned: Destroy ??? | I89: Summoned: Destroy 1 card on the field | J89: 1 ??? + 1 ??? + 800 cost | K89: 1 Divine (≥ 800 cost) + 1 Anima (≥ 800 cost) + 800 cost | L89: 00001 00010 00010 00100 01000
A90: Team Galaxos | B90: Union | D90: 85 | E90: 85 | F90: Cosmic | H90: Summoned: Until the end of foe’s turn ??? are not destroyed | I90: Summoned: Until the end of foe’s turn, Cosmic and Anima units on your side are not destroyed | J90: 1 ??? + 1 ??? + 800 cost | K90: 1 Cosmic (≥ 800 cost) + 1 Anima (≥ 800 cost) + 800 cost | L90: 01110 01000 01011 01110 00000 | M90: Yes | N90: Yes
A91: Dimensional Virus | B91: Union | D91: 0 | E91: 0 | F91: Bio | H91: Foe’s unit get ??? in Reckoning . With Mutagen Flag : ??? | I91: Foe’s unit get -10 ATK&DEF permanently in Reckoning . With Mutagen Flag : Cannot be destroyed by Non-Arcane. | J91: 1 ??? + 1 ??? + 1500 cost | K91: 1 Bio (≥ 800 cost) + 1 Arcane (≥ 800 cost) + 800 cost | L91: 10110 01001 10010 01010 00101 | M91: Yes | N91: Yes
A92: Illuminatus | B92: Union | D92: 100 | E92: 55 | F92: Arcane | H92: Summoned: +??? until the end of foe’s turn | I92: Summoned: +35 ATK&DEF until the end of foe’s turn | K92: 1 Arcane (≥ 800 cost) + 1 Divine (≥ 800 cost) + 800 cost | L92: 01111 00001 11101 00100 00100
A93: Eldritch Warlock | B93: Union | D93: 140 | E93: 65 | F93: Arcane | H93: In Reckoning, foe’s unit becomes None permanently | I93: In Reckoning, foe’s unit becomes None permanently | K93: 1 Chaos (≥ 800 cost) + 1 Arcane (≥ 800 cost) + 800 cost | L93: 00100 01010 10100 10000 01110
A94: Devilshifter | B94: Union | D94: 130 | E94: 70 | F94: Chaos | H94: Once, if this card is destroyed, ???. Affinity becomes ??? | I94: Once, if this card is destroyed, revive it at the end of this turn. Affinity becomes Anima | K94: 1 Chaos (≥ 800 cost) + 1 Anima (≥ 800 cost) + 1000 cost | L94: 00011 10001 10001 10001 11000
A95: Embodiment of Destiny | B95: Union | D95: 100 | E95: 100 | F95: Chaos | H95: Gain ??? ATK when attacking target in ??? pattern ??? | I95: Gain +60 ATK when attacking target in the same pattern as its union zone | K95: 1 Chaos (≥ 800 cost) + 1 Divine (≥ 800 cost) + 1500 cost | L95: 00100 00100 11011 00100 00100
A96: Meteorkin | B96: Union | D96: 80 | E96: 80 | F96: Nature | H96: +??? ATK for each ??? in your void | I96: +10 ATK for each Cosmic unit in your void | K96: 1 Nature (≥ 800 cost) + 1 Cosmo (≥ 800 cost) + 800 cost | L96: 01110 01010 10101 00100 00000
A97: Chainsaw Tank | B97: Union | D97: 90 | E97: 70 | F97: Anima | H97: +??? ATK vs Nature,Chaos | I97: +65 ATK vs Nature,Chaos | K97: 1 Tank unit (≥ 500 cost) + 1 Anima + 500 cost | L97: 0010 01110 00100 01110 00100
A98: Titan Tank | B98: Union | D98: 50 | E98: 60 | F98: Anima | H98: This card is unaffected by ??? | I98: This card is unaffected by trap cards | K98: 2 Tank unit + 500 cost | L98: 00111 00100 11111 00000 00000
A99: Atomic Tank | B99: Union | D99: 100 | E99: 120 | F99: Anima | H99: Once after performed attack, ??? | I99: Once after performed attack, destroy 1 card on the field. | K99: 1 Tank unit (≥ 800 cost) +1 Tank unit (≥ 500 cost) + 1000 cost | L99: 11111 01110 00100 01110 00000
A100: Mutant Queen | B100: Union | D100: 60 | E100: 180 | F100: Bio | H100: Summoned: put Mutagen Flag on ??? | I100: Summoned: put Mutagen Flag on up to 2 of your units | K100: 1 Mutant + 1 Bio + 1500 cost | L100: 10000 00001 10000 00001 10000
A101: Battle Maid Ayumi | B101: Union | D101: 40 | E101: 80 | F101: Anima | I101: Ally units in this card’s union zone gain +50 DEF | K101: 2 Battle Maid unit + 1500 cost | L101: 10001 10001 01110 01110 00000
A102: Theo the Dragon Knight | B102: Union | D102: 80 | E102: 95 | F102: Anima | I102: +20 DEF for each Dragon card on the field. +15 ATK for each Anima card on your side | K102: 1 Dragon card + 1 Anima + 800 cost | L102: 01000 01000 00110 01000 11111
A103: War Empress | B103: Union | D103: 125 | E103: 80 | F103: Anima | I103: +50 DEF to ally “Knight” cards. This card is not destroyed while there is “Knight” card on your side | K103: War Queen + 1 Knight card + 1500 cost | L103: 10101 01110 00000 00000 00000
A104: Blood Moon Mage | B104: Union | D104: 25 | E104: 50 | F104: Arcane | I104: Summoned : Average both player’s crystal | K104: 1 Mage card + 1 Moon card + 500 cost | L104: 00000 01110 10001 10001 01110
A105: Moon Knight | B105: Union | D105: 90 | E105: 50 | F105: Anima | I105: None | K105: 1 Moon card + 1 Anima + 500 cost | L105: 00000 01111 10100 10100 01111
A106: Priestess of the Moon | B106: Union | D106: 0 | E106: 0 | F106: Divine | I106: Summoned : +300 crystals per exposed divine unit in your field | K106: 1 Moon card + 1 Divine + 500 cost | L106: 00100 01110 00100 01000 01111
A107: Moon Shifter | B107: Union | D107: 0 | E107: 70 | F107: Nature | I107: In Reckoning, average foe’s ATK and DEF until the end of your turn. | K107: 1 Moon card + 1 Nature + 500 cost | L107: 00100 10001 01010 00100 01010
A108: Europan Emperor | B108: Union | D108: 180 | E108: 80 | F108: Cosmic | I108: This card cannot attack without Europa Flag. After attacked, remove Europa Flag from this card. | K108: 1 Europan card with Europa Flag+ 1 Cosmic + 1000 cost | L108: 10001 01010 10001 01010 00100
A109: Carbon Behemoth | B109: Union | D109: 195 | E109: 100 | F109: Cosmic | I109: None | K109: 3 Cosmic card (≥ 800 cost) + 1000 cost | L109: 00000 00000 11011 0101 11111
A110: Solarflare Dragon | B110: Union | D110: 140 | E110: 120 | F110: Cosmic | I110: Summoned : Foe choose and reveal 3 cards. You gain 500 crystals per Dead-End among them. | K110: Solarling + 1 Cosmic card (≥ 800 cost) + 1200 cost | L110: 10101 01010 10001 01010 10001
A111: Nanomites Rafflesia | B111: Union | D111: 30 | E111: 30 | F111: Bio | I111: Summoned : +2000 crystals | K111: 1 Nanomites card + 1 Bio (≥ 800 cost) + 1500 cost | L111: 00000 00000 10001 10001 11111
A112: Gamma Kraken | B112: Union | D112: 75 | E112: 50 | F112: Bio | I112: Summoned: gain 1 attack count for this turn. With Mutagen Flag: This card can attack twice. | K112: 1 Gamma cards + 2 Bio (≥ 500 cost) + 1000 cost | L112: 00000 01010 01010 01010 00100
A113: Mutant Soldier | B113: Union | D113: 55 | E113: 65 | F113: Bio | I113: With Mutagen Flag : +100 ATK | K113: 1 Mutant cards + 1 Bio (≥ 500 cost) + 500 cost | L113: 00000 10101 10101 10101 00000
A114: Mistress-001 | B114: Union | D114: 100 | E114: 50 | F114: Bio | I114: Summoned: select 1 other face-up card on the field, it gain +50 ATK, but get -50 DEF | J114: 2 ??? + 500 cost | K114: 2 Bio cards with number in its name + 500 cost | L114: 11100 00100 00100 00100 00100
A115: Enormous Slime | B115: Union | D115: 45 | E115: 45 | F115: Bio | I115: This card is not destroyed by Anima or Bio card | K115: 1 Slime + 1 Bio (≥ 500 cost) + 500 cost | L115: 00000 01110 01110 11111 00000
A116: House of Flesh | B116: Union | D116: 0 | E116: 0 | F116: Chaos | I116: This card can only be destroyed by Chaos or Divine unit | K116: Red Closet + 1 Chaos (≥ 800 cost) + 1500 cost | L116: 00100 01010 10001 00000 11111
A117: Eye in the Sky | B117: Union | D117: 0 | E117: 0 | F117: Chaos | I117: Summoned: Reveal 1 card per unit in your void | K117: Drifting Head + 1 Chaos + 500 cost | L117: 01110 10001 00100 10001 01110
A118: Bloody Mask | B118: Union | D118: 55 | E118: 25 | F118: Chaos | I118: None | K118: Jacob the Ski Mask + Franky the Steel Claw + 200 cost | L118: 11011 11011 00000 10001 01110
A119: Cthulhu | B119: Union | D119: 110 | E119: 150 | F119: Chaos | I119: -50 ATK&DEF to foe unit in this card’s Union Zone pattern | K119: Blood Mage + Chaos (≥ 1000 cost) + 1200 cost) | L119: 00000 01110 01110 10101 00100
A120: Supreme Lich | B120: Union | D120: 25 | E120: 25 | F120: Chaos | I120: +10 ATK&DEF for each or your revealed cells | K120: 1 Lich card + 1 Chaos + 1000 cost | L120: 01110 00110 00010 00010 00010
A121: Siege Engine | B121: Union | D121: 50 | E121: 55 | F121: Anima | I121: Once, destroy defending unit in Reckoning | K121: 1 Anima (≥ 800 cost) + 2 Anima (≥ 500 cost) + 800 | L121: 11000 11000 00000 00001 01111
A122: Ultimate Railgun | B122: Union | D122: 200 | E122: 150 | F122: Anima | I122: Can only attack if there is only Railgun Ammo in your void | K122: 1 Railgun card + 1 Anima + 1000 cost | L122: 00000 01000 00100 00010 11110
A123: The Last Paladin | B123: Union | D123: 10 | E123: 10 | F123: Anima | I123: +300 ATK&DEF if 15 or more cells on your side are revealed | K123: 1 Knight card + 1 Anima Card + 0 cost | L123: 00100 00100 11111 00100 00100
A124: Desperado | B124: Union | D124: 40 | E124: 30 | F124: Anima | I124: After it performed attack, flip a coin. Heads: +20 ATK permanently. | K124: Johnny the Most Wanted + 1 Anima + 500 cost | L124: 00000 11111 11111 10000 00000
A125: Raijin Fujin and Suijin | B125: Union | D125: 145 | E125: 145 | F125: Divine | H125: At the start of each player’s turn, they choose either destroy ??? or lose ??? crystals. | I125: At ??? turn, they choose either destroy ??? or lose ??? | J125: 1 ??? + 1 ??? + 800 cost | K125: Raijin + Fujin + Suigin + 1200 cost | L125: 10101 10101 10101 10101 10101
A126: Raijin Fujin and Suigin | B126: Union | D126: 145 | E126: 145 | F126: Divine | H126: Summoned : Both player destroy ???. | I126: Summoned : Both player destroy 3 of ??? | J126: 1 ??? + 1 ??? + 800 cost | K126: Raijin + Fujin + Suigin + 1200 cost | L126: 10101 10101 10101 10101 10101
A127: Death Parasite | B127: Union | D127: 0 | E127: 0 | F127: Bio | H127: +15 ATK&DEF for each ???. In Reckoning with Cosmic unit, this card get ??? | I127: +15 ATK&DEF for each units on the field. In Reckoning with Cosmic unit, this card get -50 DEF | J127: 2 ??? + 1000 cost | K127: 2 Parasite card + 1000 cost | L127: 00001 11110 00000 01111 10000
A128: Ultimate Zombie | B128: Union | D128: 100 | E128: 65 | F128: Bio | H128: Mutagen Flag : If this card is destroyed, ??? | I128: Mutagen Flag : If this card is destroyed, also destroy foe’s unit | J128: 2 ??? + 1000 cost | K128: 2 Parasite card + 1000 cost | L128: 00001 11110 00000 01111 10000
A129: Dark Surgeon | B129: Union | D129: 0 | E129: 50 | F129: Chaos | H129: Summoned : Revive ??? | I129: Summoned : Revive 1 unit. Its DEF becomes 0 | J129: ??? + ??? + 800 cost | K129: Mad Doctor + Wicked Nurse + 800 cost | L129: 00000 00100 01110 00100 00000
...

Sheet Trap
A1: Table 1
A2: Card Name | B2: Card Type | C2: Cost | D2: ATK | E2: DEF | F2: Affinity | G2: Rarity | H2: Ability | I2: Formula | J2: Have illustration | K2: Suggested cost | L2: Demo | M2: Test 1 | N2: ="Booster Pack - Blightsilver / "&COUNTIF(N3:N544,"Yes") -> Booster Pack - Blightsilver / 8 | O2: ="Booster Pack - Unseen Presence / "&COUNTIF(O3:O544,"Yes") -> Booster Pack - Unseen Presence / 8 | P2: ="Booster Pack - Wind of Dominance / "&COUNTIF(P3:P544,"Yes") -> Booster Pack - Wind of Dominance / 5
A3: Trap Hole | B3: Trap | C3: 0 | G3: 1 | H3: Flip 3 coin, attacking player loses 20 Crystals per each head(s). | J3: Yes | L3: Yes
A4: Hostage | B4: Trap | C4: 500 | G4: 2 | H4: Usable when foe attacks. You can reveal one of your unit. Until this turn ends, foe cannot target that unit. If already targeted it, foe must choose other cell. | J4: Yes | L4: Yes | N4: Yes
A5: Bait | B5: Trap | C5: 0 | G5: 1 | H5: You choose one other cell on your side and reveal it. | J5: Yes | L5: Yes | N5: Yes
A6: Blackmail | B6: Trap | C6: 0 | G6: 2 | H6: The attacker chooses either discarding 1 Tech Card or end the turn immediately | J6: Yes | L6: Yes | N6: Yes
A7: Cursed Reflection | B7: Trap | C7: 600 | G7: 3 | H7: Swap the attacking unit's ATK&DEF until the end of your turn. | J7: Yes | L7: Yes | O7: Yes
A8: Explosive Barrels | B8: Trap | C8: 0 | G8: 5 | H8: Destroy the attacking unit. You also pay the same cost as attacker. | J8: Yes | L8: Yes | P8: Yes
A9: Hypnosis | B9: Trap | C9: 500 | G9: 4 | H9: The attacking unit cannot attack during the foe's next turn. | J9: Yes | L9: Yes | N9: Yes
A10: Flame Trap | B10: Trap | C10: 200 | G10: 2 | H10: The attacking unit gets -10 ATK permanently. | J10: Yes | L10: Yes | O10: Yes
A11: Echo Barrier | B11: Trap | C11: 400 | G11: 3 | H11: This turn, foe cannot perform any more attack. | J11: Yes | L11: Yes | O11: Yes
A12: Mana Drain | B12: Trap | C12: 200 | G12: 2 | H12: Foe loses 300 Crystals. You gain 300 Crystals. | J12: Yes | L12: Yes
A13: Defensive Pheromone | B13: Trap | C13: 400 | G13: 3 | H13: You switch 1 'Armored' Nature card on your side with this cell, then repeat Reckoning. | J13: Yes | L13: Yes | O13: Yes
A14: Spike Trap | B14: Trap | C14: 800 | G14: 5 | H14: Destroy the attacking unit | J14: Yes | L14: Yes | P14: Yes
A15: Snare Trap | B15: Trap | C15: 500 | G15: 4 | H15: The attacking unit's ability becomes None until attacker’s next turn ends | J15: Yes | L15: Yes | P15: Yes
A16: Brainwash | B16: Trap | C16: 800 | G16: 5 | H16: The attacker chooses their own ally as an attack target | J16: Yes | L16: Yes | O16: Yes
A17: Bunker | B17: Trap | C17: 800 | G17: 4 | H17: Usable when foe attack this card or surround cells. Foe cannot target surrounding cells until the end of this turn. If already targeted, they must choose other cell. | J17: Yes | L17: Yes | P17: Yes
A18: Foul Gas | B18: Trap | C18: 0 | G18: 3 | H18: -5 ATK to all the attacking player’s units until the end of this turn | J18: Yes | L18: Yes | N18: Yes
A19: Choking Gas | B19: Trap | C19: 200 | G19: 4 | H19: -20 ATK to all the attacking player’s units until the end of this turn | J19: Yes | L19: Yes
A20: Radiation | B20: Trap | C20: 600 | G20: 4 | H20: Attacking unit permanently lose 10 ATK&DEF. it loses more 10 ATK&DEF for each trap cards in your void | J20: Yes | L20: Yes
A21: Acid Trap Hole | B21: Trap | C21: 0 | G21: 1 | H21: Flip 2 coin, attacking player loses 50 Crystals per each head(s). | J21: Yes | L21: Yes | N21: Yes
A22: Lava Trap Hole | B22: Trap | C22: 50 | G22: 2 | H22: Flip 3 coin, attacking player loses 100 Crystals per each head(s). | J22: Yes | L22: Yes
A23: Fissure | B23: Trap | C23: 100 | G23: 3 | H23: Attacking player loses 200 Crystals | J23: Yes
A24: Soul Blast | B24: Trap | C24: 800 | G24: 5 | H24: Attacking player lose 150 Crystals for each unit cards in your void | J24: Yes | L24: Yes
A25: Grudge | B25: Trap | C25: 600 | G25: 2 | H25: -10 ATK to the attacking unit permanently for each unit cards in your void | J25: Yes | L25: Yes
A26: Anti-virus | B26: Trap | C26: 400 | G26: 1 | H26: If attacker is Bio, flip a coin. Head: destroy it. Always head, if your Crystal is 1000 or less. | J26: Yes
A27: Witch Hunt | B27: Trap | C27: 400 | G27: 1 | H27: If attacker is Arcane, flip a coin. Head: destroy it. Always head, if your Crystal is 1000 or less. | J27: Yes
A28: Standoff | B28: Trap | C28: 400 | G28: 1 | H28: If attacker is Anima, flip a coin. Head: destroy it. Always head, if your Crystal is 1000 or less. | J28: Yes
A29: Apple of Adam | B29: Trap | C29: 400 | G29: 1 | H29: If attacker is Divine, flip a coin. Head: destroy it. Always head, if your Crystal is 1000 or less. | J29: Yes
A30: Purify | B30: Trap | C30: 400 | G30: 1 | H30: If attacker is Chaos, flip a coin. Head: destroy it. Always head, if your Crystal is 1000 or less. | J30: Yes
A31: Solar Flare | B31: Trap | C31: 400 | G31: 1 | H31: If attacker is Cosmic, flip a coin. Head: destroy it. Always head, if your Crystal is 1000 or less. | J31: Yes
A32: Hunting Season | B32: Trap | C32: 400 | G32: 1 | H32: If attacker is Nature, flip a coin. Head: destroy it. Always head, if your Crystal is 1000 or less. | J32: Yes
A33: Dart Trap | B33: Trap | C33: 350 | G33: 2 | H33: If the attacking unit is the first one to attack in that turn, -50 DEF | J33: Yes
A34: Science Cage | B34: Trap | C34: 250 | G34: 3 | H34: If attacker Is Bio affinity, end their turn immediately. Remove all flags from it. | J34: Yes
A35: Loop Hole | B35: Trap | C35: 250 | G35: 3 | H35: If attacker is Arcane, its ability become None permanently. | J35: Yes
A36: Talisman of Light | B36: Trap | C36: 250 | G36: 3 | H36: If attacker is Chaos, -50 ATK to that unit permanently | J36: Yes
A37: Forbidden Grail | B37: Trap | C37: 250 | G37: 3 | H37: If attacker is Divine, -50 DEF to that unit permanently | J37: Yes
... A40: Galaxy Toll | B40: Trap | C40: 250 | G40: 3 | H40: If attacker is Cosmic, foe loses 1000 Crystals | J40: Yes
A41: Union Cage | B41: Trap | C41: 400 | G41: 3 | H41: Usable if a Union card attack this card or the surround cell. That Union card cannot attack until the attacker’s next turn ends. | J41: Yes | L41: Yes
A42: Plunder | B42: Trap | C42: 500 | G42: 4 | H42: The attacker chooses to let you receive 1000 Crystals, or destroy the attacking unit. | J42: Yes | L42: Yes
A43: Decoy Puppet | B43: Trap | C43: 100 | G43: 2 | H43: This turn, attacker cannot perform any more attack using unit with 400 or less cost. | J43: Yes | L43: Yes | O43: Yes
A44: Hard Scale | B44: Trap | C44: 300 | G44: 1 | H44: All of your unit gain +5 DEF in Reckoning until attacker’s next turn ends | J44: Yes | L44: Yes
A45: Steel Scale | B45: Trap | C45: 500 | G45: 1 | H45: All of your units gain +15 DEF in Reckoning until attacker’s next turn ends
A46: Trick Door | B46: Trap | C46: 300 | G46: 1 | H46: You select 1 of your unit and swap or relocate to any cell. Repeat Reckoning if it’s this cell.
A47: Boiling Oil | B47: Trap | C47: 400 | G47: 1 | H47: All of attacker’s unit get -10 ATK&DEF until your turn ends.
A48: Lightning Rod | B48: Trap | C48: 0 | G48: 3 | H48: Foe loses 1000 Crystals if they target this card with any tech card
A49: Dreamcatcher | B49: Trap | C49: 400 | G49: 5 | H49: When foe use a tech card, this card can be triggered. That tech card effect is cancelled.
A50: Stumble | B50: Trap | C50: 100 | G50: 1 | H50: Attacker ends your turn immediately. If attacker has any remaining attack, they are transferred to their next turn.
A51: Ruckus | B51: Trap | C51: 0 | G51: 1 | H51: Until the end of your turn, All exposed Bio units gain +5 ATK
A52: Red Card | B52: Trap | C52: 0 | G52: 2 | H52: Flip 2 coins. If both are heads, that unit cannot attack until the foe's next turn ends. | J52: Yes | L52: Yes | O52: Yes
A53: Counter Punch | B53: Trap | C53: 0 | G53: 2 | H53: Attacking unit get -5 DEF until the end of your turn
A54: Counter Tackle | B54: Trap | C54: 400 | G54: 3 | H54: Attacking unit get -15 DEF until the end of your turn
A55: Street Joke | B55: Trap | C55: 0 | G55: 1 | H55: You reveal 1 of your cell, you receive 100 Crystal | J55: Yes | L55: Yes | N55: Yes
A56: Alarm | B56: Trap | C56: 0 | G56: 1 | H56: Until your turn ends, All your Anima units gain +10 ATK&DEF in Reckoning | J56: Yes | L56: Yes | N56: Yes
A57: Self-destruct | B57: Trap | C57: 0 | G57: 2 | H57: You select 1 of your unit. +50 ATK&DEF until your turn ends, but also destroy it. You pay no cost. | J57: Yes | L57: Yes | P57: Yes
A58: Rank C Bounty | B58: Trap | C58: 0 | G58: 2 | H58: The attacker’s cost is increased by 100 until the end of your turn.
A59: Pepper Spray | B59: Trap | C59: 0 | G59: 1 | H59: Flip 2 coins. The attacking unit get -5 ATK for each heads until the foe's next turn ends. | J59: Yes | L59: Yes | O59: Yes
A60: Share the Pain | B60: Trap | C60: 0 | G60: 5 | H60: If you has 1000 or less Crystal, average both player’s Crystals.
A61: Tripwire | B61: Trap | C61: 100 | G61: 2 | H61: Destroy the attacker with 20 or less ATK. Attacker side pay no cost.
A62: Soak Wet | B62: Trap | C62: 200 | G62: 2 | H62: Flip 4 coins. The attacking unit get -5 DEF for each heads until your turn ends.
A63: Supersonic | B63: Trap | C63: 200 | G63: 2 | H63: Flip 4 coins. The attacking unit get -5 ATK for each heads until the foe's next turn ends.
A64: Kill Zone | B64: Trap | C64: 150 | G64: 2 | H64: Destroy the attacker with 50 or less ATK. Attacker side pay no cost.
A65: Boulder Trap | B65: Trap | C65: 0 | G65: 2 | H65: Destroy the attacker with 20 or less DEF. Attacker side pay no cost.
A66: Rank S Bounty | B66: Trap | C66: 500 | G66: 2 | H66: The attacker’s cost is doubled until the end of your turn.
A67: Flimsy Ground | B67: Trap | C67: 700 | G67: 2 | H67: If any Dead-end surrounding this card is being attacked, turn this card face-up, flip a coin. Heads: destroy the attacking unit. Attacker pay no cost
A68: Shaky Ground | B68: Trap | C68: 300 | G68: 3 | H68: If any Dead-end surrounding this card is being attacked, turn this card face-up, attacking unit get -5 DEF permanently
A69: Anti-intelligence | B69: Trap | C69: 0 | G69: 3 | H69: If foe use any effect that reveal your cell, turn this card face-up and cancel it.
A70: Amnesia | B70: Trap | C70: 600 | G70: 4 | H70: If foe’s unit triggered any ability, turn this card face-up. Its ability becomes None until the end of this turn.
A71: Confiscate | B71: Trap | C71: 0 | G71: 2 | H71: If foe use any effect that increase Crystal, flip this card face-up and cancel it.
... A74: The House Always Win | B74: Trap | C74: 250 | G74: 5 | H74: If foe use any effect that flip a coin, turn this card face-up, that effect lands on Tail.
A75: Ancestral Spirit | B75: Trap | C75: 500 | H75: Whenever Tribe unit on your side is destroyed, you can flip this card face-up and revive that unt.
A76: Midlife Crisis | B76: Trap | C76: 350 | H76: Attacker’s ability becomes None until the end of your turn.
A77: Underpay | B77: Trap | C77: 100 | H77: Attacker’s ability becomes “The cost of this card is halved” permanently
A78: Discount | B78: Trap | C78: 300 | H78: The cost of all units on your side is halved until the end of this turn.
A79: Rift Trap | B79: Trap | C79: 200 | H79: If any unit trigger relocation ability, turn this card face-up then destroy it.
A80: Substitute Player | B80: Trap | C80: 200 | H80: Your foe choose another of their unit, swap location with the Attacker, then repeat Reckoning.
A81: Disunite | B81: Trap | C81: 500 | H81: Destroy Union attack. Revive units used for union summon. Their cost becomes 0.
A82: Union Checkpoint | B82: Trap | C82: 500 | H82: Once foe summoned Union card, turn this card face-up. That Union card cannot attack during this turn.
A83: Tear Gas | B83: Trap | C83: 200 | H83: Flip 4 coins. All foe’s unit get -10 ATK for each heads until the end of this turn.
A84: Flashbang | B84: Trap | C84: 250 | H84: Flip 3 coins. Select foe’s unit up to number of heads. Those unit s cannot attack until the end of this turn.
A85: Taser | B85: Trap | C85: 250 | H85: Flip 2 coins. The attacking unit get -10 DEF for each heads until the end of your turn
A86: Rank B Bounty | B86: Trap | C86: 100 | G86: 2 | H86: The attacker’s cost is increased by 250 until the end of your turn.
A87: Rank A Bounty | B87: Trap | C87: 250 | G87: 2 | H87: The attacker’s cost is increased by 500 until the end of your turn.
A88: Inferno Trap | B88: Trap | C88: 600 | G88: 2 | H88: The attacking unit gets -25 ATK permanently.
A89: Trap Dealer | B89: Trap | C89: 0 | H89: This turn, all of your trap cost becomes 0.
A90: Play Zone | B90: Trap | C90: 100 | H90: Until your turn ends, all unit cost becomes 0.
A91: Evacuation Zone | B91: Trap | C91: 200 | H91: Until the end of this turn, cost of all Anima cards on your side is halved.
A92: 13th Night | B92: Trap | C92: 250 | H92: Revive 1 Chaos monster from your void on this cell and repeat Reckoning
A93: Union Safeguard | B93: Trap | C93: 200 | H93: Relocate Union card on your side to this cell and repeat Reckoning.
A94: Infestation | B94: Trap | C94: 300 | H94: Destroy 1 parasite or worm unit on your field (you pay no cost). Select 1 face-up unit on foe’s side and repeat Reckoning with the attacker.
A95: Gamma Trap | B95: Trap | C95: 200 | H95: If there is Gamma or Radia unit on your side, -20 DEF to the attacker permanently.
A96: Poisonous Tea | B96: Trap | C96: 500 | H96: Foe gain 1000 crystals. They lose 1500 crystals at the end of their next turn.
A97: Elven Arrow Trap | B97: Trap | C97: 600 | H97: If there is face-up Elven unit on your side, destroy the attacker.
A98: Zantetsuken | B98: Trap | C98: 500 | H98: If there is face-up Swordsman unit on your side, destroy the attacker.
A99: Bone Trap | B99: Trap | C99: 150 | H99: If there is face-up Skeleton unit on your side, halve attacker’s ATK&DEF permanently.
A100: Golem Reconstruction | B100: Trap | C100: 600 | H100: If your Golem unit is destroyed, you can turn this card face-up, revive it at the end of this turn.
... A115: Dawnbreak | B115: Trap | C115: 100 | H115: Reveal 1 cells on opponent’s side.

Sheet Tech
A1: Table 1
A2: Card Name | B2: Card Type | C2: Cost | D2: ATK | E2: DEF | F2: Affinity | G2: Rarity | H2: Ability | I2: Formula | J2: Illustration | K2: Suggested cost | L2: Demo | M2: Test 1 | N2: ="Booster Pack - Blightsilver / "&COUNTIF(N3:N545,"Yes") -> Booster Pack - Blightsilver / 4 | O2: ="Booster Pack - Unseen Presence / "&COUNTIF(O3:O545,"Yes") -> Booster Pack - Unseen Presence / 2 | P2: ="Booster Pack - Wind of Dominance / "&COUNTIF(P3:P545,"Yes") -> Booster Pack - Wind of Dominance / 5
A3: Welcoming Door | B3: Tech | C3: 0 | G3: 1 | H3: Choose any square on your side and reveal it | J3: Yes
A4: Spy | B4: Tech | C4: 0 | G4: 1 | H4: Reveal 1 of foe’s cell | J4: Yes | L4: Yes
A5: Ceasefire | B5: Tech | C5: 0 | G5: 3 | H5: Both players skip 1 turn (tax is forced to apply) | J5: Yes
A6: Make Friend | B6: Tech | C6: 0 | G6: 5 | H6: Both players select 1 unit from their side. That unit cannot attack until your next turn ends | J6: Yes
A7: Double Spy | B7: Tech | C7: 0 | G7: 2 | H7: Only trigger if you have Spy card in the void. Reveal 2 cells on foe's side. | J7: Yes
A8: Invisible Spy | B8: Tech | C8: 0 | G8: 3 | H8: Only trigger if you have Double Spy card in the void. Reveal 2 cells on foe's side. | J8: Yes
A9: Corrupted Spy | B9: Tech | C9: 0 | G9: 4 | H9: Reveal 3 cells on foe’s side. If any trap or unit is found, you pays 700 Crystal for each card found. | J9: Yes
A10: Tease | B10: Tech | C10: 0 | G10: 2 | H10: Foe chooses and reveal 1 of their cell | J10: Yes | L10: Yes
A11: Bribe | B11: Tech | C11: 0 | G11: 3 | H11: Foe can choose to reveal a unit card and receive 700 Crystals or do nothing | J11: Yes | L11: Yes | N11: Yes
A12: Release Mutagen | B12: Tech | C12: 0 | G12: 4 | H12: Add Mutagen Flag to 1 of your unit | J12: Yes | L12: Yes | O12: Yes
A13: Prayer | B13: Tech | C13: 0 | G13: 4 | H13: Once, until foe’s turn ends: prevent Divine card from being destroyed | J13: Yes | L13: Yes | O13: Yes
A14: Arcane Nova | B14: Tech | C14: 2500 | G14: 5 | H14: Destroy up to 3 exposed foe units (no cost is paid). You discard all of your tech cards afterward. | J14: Yes
A15: Rift Strike | B15: Tech | C15: 2000 | G15: 3 | H15: Select 3 adjacent cells on foe’s field and destroy it. No cost is paid | J15: Yes | L15: Yes
A16: Great Diplomacy | B16: Tech | C16: 1000 | G16: 4 | H16: You select up to 3 of your units and reveal them. | J16: Yes | L16: Yes | P16: Yes
A17: War Supply | B17: Tech | C17: 1000 | G17: 3 | H17: Your units get +10 ATK&DEF in Reckoning until the end of the turn. | J17: Yes | L17: Yes | N17: Yes
A18: Harsh Training | B18: Tech | C18: 500 | G18: 2 | H18: Select 1 of your units. It gains +10 ATK permanently. | J18: Yes | N18: Yes
A19: Illegal Steroid | B19: Tech | C19: 1000 | G19: 4 | H19: +30 ATK for 1 unit until the end of this turn. | J19: Yes
A20: Secret Dagger | B20: Tech | C20: 600 | G20: 3 | H20: Can only be used on face-down card. Turn that card exposed and +15 ATK until the end of this turn. | J20: Yes
A21: Garrison | B21: Tech | C21: 1500 | G21: 4 | H21: Until foe's turn ends: +20 DEF to all your cards in Reckoning | J21: Yes | L21: Yes
A22: Bulletproof Vest | B22: Tech | C22: 850 | G22: 3 | H22: +15 DEF permanently for 1 exposed unit. If use on face-down card, flip it up. | J22: Yes
A23: Siege Cannon | B23: Tech | C23: 1000 | G23: 5 | H23: Until the end of this turn, once, foe’s defending unit is destroyed. | J23: Yes | L23: Yes | P23: Yes
A24: Assassinate | B24: Tech | C24: 1500 | G24: 4 | H24: Destroy 1 of foe’s exposed card | J24: Yes
A25: Accident | B25: Tech | C25: 1000 | G25: 3 | H25: Destroy 1 of foe’s exposed card. If there is no exposed card, foe must choose the target. foe pays no cost. | J25: Yes | L25: Yes | P25: Yes
A26: Berserk | B26: Tech | C26: 900 | G26: 5 | H26: You gain 1 attack count until the end of this turn | J26: Yes | L26: Yes
A27: Radar | B27: Tech | C27: 600 | G27: 1 | H27: Reveal 3 of foe’s cell | J27: Yes | L27: Yes | N27: Yes
A28: Palace Party | B28: Tech | C28: 500 | G28: 2 | H28: You reveal 1 face-down unit. Foe must reveal 1 of their face-down unit (if any) | J28: Yes
A29: Essence Transfer | B29: Tech | C29: 700 | G29: 5 | H29: You chooses 1 unit. Copy all its ATK&DEF bonuses or debuffs to another ally unit (if valid) until the end of this turn. | J29: Yes
A30: Blood Ritual | B30: Tech | C30: 1000 | G30: 4 | H30: Destroy 1 card on your side (No paid cost). Choose 1 of foe's exposed unit. Its ATK&DEF becomes 0 permanently | J30: Yes
A31: Arcane Duplication | B31: Tech | C31: 1000 | G31: 5 | H31: You. Choose 1 unit. Create a token copy of it on an empty cell. Destroy it at the end of your next turn. | J31: Yes
A32: Time Travel | B32: Tech | C32: 1800 | G32: 5 | H32: Once only, revive 1 unit to any unoccupied or empty cell in exposed position. Double its Crystal cost. | J32: Yes
A33: Resurrection | B33: Tech | C33: 1500 | G33: 4 | H33: Once, revive 1 unit. It has no ATK,DEF, or ability. | J33: Yes | L33: Yes | P33: Yes
A34: Tech Copy | B34: Tech | C34: 1000 | G34: 3 | H34: Foe show 1 tech card in their hand. Add a copy of that card into your Tech Stack.
A35: Force Shield | B35: Tech | C35: 600 | G35: 2 | H35: You selects 1 unit. It is not destroyed until the end of foe's turn
A36: Wisp Light | B36: Tech | C36: 250 | G36: 3 | H36: Destroy as many ally ‘wisp’ units. Reveal that much cells on foe's side.
A37: Lucky Day | B37: Tech | C37: 300 | G37: 2 | H37: Flip a coin. If head, receive 600 Crystals. Always head, if your Crystal is 1000 or less.
A38: Immortal Blood | B38: Tech | C38: 1000 | G38: 3 | H38: Revive 1 immortal vampire or vampire servant.
A39: Yin Yang Swap | B39: Tech | C39: 1200 | G39: 4 | H39: Swap ATK&DEF on 1 exposed unit until the end of this turn
A40: Coin on the Street | B40: Tech | C40: 0 | G40: 1 | H40: Receive 20 Crystals
A41: Bank Note on the Street | B41: Tech | C41: 0 | G41: 2 | H41: Receive 50 Crystals
A42: Casual Gambling | B42: Tech | C42: 0 | G42: 1 | H42: Flip a coin. If head, receive 100 Crystals.
A43: Degen Gambling | B43: Tech | C43: 0 | G43: 2 | H43: Flip a coin. If head, receive 200 Crystals. If tail, lose 400 Crystals
A44: Gift | B44: Tech | C44: 0 | G44: 1 | H44: Foe receive 50 Crystals
A45: Hired Spanker | B45: Tech | C45: 0 | G45: 2 | H45: Until the end of foe's turn, if foe attack a bluffed cell, foe receive 800 Crystals.
... A81: Rugpull | B81: Tech | C81: 500 | G81: 5 | H81: Both players lose 2000 Crystals. Discard all tech in your hands.
A82: Crack the Whip | B82: Tech | C82: 1000 | G82: 2 | H82: Once, your attacking unit can attack twice. But it cannot attack again until the end of your next turn. | J82: Need Revise
A83: Full open fire | B83: Tech | C83: 1500 | G83: 4 | H83: Both players gain 2 additional attack for one of your turn.
A84: Service Charge | B84: Tech | C84: 300 | G84: 1 | H84: Until the end of foe's turn. Foe have to pay 50 Crystal tax to perform an attack.
A85: Lazy Scout | B85: Tech | C85: 200 | G85: 1 | H85: Reveal 1 foe’s cell. You cannot perform any attack. Cannot use this card if already attacked.
A86: Last Gambit | B86: Tech | C86: 0 | G86: 1 | H86: If you has 5 or less cards on your side, destroy 1 foe’s card.
A87: Trash Penalty | B87: Tech | C87: 0 | G87: 1 | H87: Foe chooses either clearing all of their bluffs and flags, or they lose 500 crystals
A88: Silence Zone | B88: Tech | C88: 500 | G88: 1 | H88: Clear all bluffs from both players. No one can use bluff ever again during this duel.
A89: Bare Fist Fight | B89: Tech | C89: 0 | G89: 1 | H89: Both players select and discard 1 tech card from their hand.
A90: Mine Detector | B90: Tech | C90: 500 | G90: 2 | H90: Reveal 1 card on foe's side. If it’s a trap, destroy it and gain 200 Crystals
A91: Natural Healing | B91: Tech | C91: 0 | G91: 2 | H91: If all exposed ally units are Nature card, gain 50 Crystals for each of them
A92: Third Eye | B92: Tech | C92: 600 | G92: 2 | H92: If this is the last tech card on your hand, reveal 3 cards on foe's side
A93: Punching Bag | B93: Tech | C93: 500 | G93: 2 | H93: 1 ally unit’s ATK&DEF becomes 0 permanently. It cannot be destroyed until the end of foe’s turn.
A94: Scattered Shot | B94: Tech | C94: 2000 | G94: 4 | H94: Flip 3 coins. Destroy foe’s exposed unit equal to number of heads. foe pays no cost. | J94: Yes
A95: Spotlight | B95: Tech | C95: 1500 | G95: 4 | H95: Flip 5 coins. Reveal foe’s cell equal to number of heads
A96: Tight Door | B96: Tech | C96: 0 | G96: 1 | H96: Next turn, foe can attack only once
A97: Katana Strike | B97: Tech | C97: 2000 | G97: 3 | H97: Select 1 exposed foe’s card. Destroy other exposed cards on that same columns as the selected cell. Foe pays no cost
A98: Mining Season | B98: Tech | C98: 300 | H98: Until foe’s turn ends, both players can only target face-down card
A99: Throne Duel | B99: Tech | C99: 800 | H99: Until foe’s turn ends, both players can only attack with unit with 800 or more cost. Cannot use if already attacked.
A100: Joint Maneuver | B100: Tech | C100: 600 | H100: Until foe’s turn ends, both players can only attack with unit with 600 or less cost. Cannot use if already attacked.
A101: Pillow Fight | B101: Tech | C101: 300 | H101: Until foe’s turn ends, both players can only attack with unit with 300 or less cost. Cannot use if already attacked.
A102: Army Reformation | B102: Tech | C102: 500 | H102: Swap or relocate 1 unit to any cell.
A103: Institutionalization | B103: Tech | C103: 1000 | H103: Target 1 unit on either’s side. Its ability becomes None until foe’s turn ends
A104: Potent Poison | B104: Tech | C104: 1000 | H104: Select 1 card with Venom Flag. Double its cost, then destroy it. | L104: Yes | P104: Yes
A105: Railgun Ammo | B105: Tech | C105: 1500 | H105: Once, your Railgun card’s ATK is doubled in Reckoning
A106: Inflation | B106: Tech | C106: 800 | H106: Select 1 exposed unit on the field. Double its cost permanently
A107: Conscription | B107: Tech | C107: 0 | G107: 2 | H107: All Anima unit costs are halved until the start of your next turn.
A108: Dark Ritual | B108: Tech | C108: 0 | G108: 2 | H108: Destroy 1 of your Chaos units. You do not pay cost.
A109: Arcanization | B109: Tech | C109: 0 | G109: 5 | H109: Select 1 unit on either player’s field, that unit becomes Arcane Affinity until the end of this turn
A110: CMB Wave | B110: Tech | C110: 0 | G110: 3 | H110: Choose either: Reveal 1 of your Cosmic unit, or +5 ATK to all of your unit per 2 cards revealed on your side
A111: Bloody Machete | B111: Tech | C111: 0 | H111: If you have ‘Bloody Mask’ on your side, destroy 1 face-up unit.
A112: Simple Unity | B112: Tech | C112: 500 | H112: If you have Union card with None ability, destroy 1 card on the field.
A113: Nanomites Outbreak | B113: Tech | C113: 500 | H113: Double cost of foe’s unit up to number of Nanomites unit on your side
A114: Zombie Outbreak | B114: Tech | C114: 500 | H114: Foe’s unit up to number of Mutant or Zombie unit on your side, get -50 DEF
A115: Europa Supply | B115: Tech | C115: 300 | H115: Put 1 Europa Flag on your unit
A116: Simple Sword | B116: Tech | C116: 500 | H116: +20 ATK&DEF to 1 unit on your side with None ability until the end of foe’s turn
A117: Slim Gray Ray | B117: Tech | C117: 600 | H117: If you have 1 face-up Slim Gray on your side, both player reveal 1 of their own cells
A118: Oni Slam | B118: Tech | C118: 1000 | H118: If you have face-up Oni card on your side, destroy 1 card on your foe’s field.
A119: Knight’s Oath | B119: Tech | C119: 1000 | H119: Until the end of foe's turn, Knight units are not destroyed.
A120: Advanced Medicine | B120: Tech | C120: 1000 | H120: If you have face-up Doctor or Healer card on your field, you gain 1800 crystals
A121: Warrior’s Oath | B121: Tech | C121: 600 | H121: Select 1 face-up Warrior card on your side, it gain +40 ATK
A122: Dragon’s Breath | B122: Tech | C122: 1500 | H122: If you have face-up Dragon card on your field, destroy 2 cards on the field. Foe pay no cost.
... A133: Lex Purgatoria | B133: Tech | C133: 800 | H133: Until the end of foe’s turn, destroy any Arcane unit in Reckoning with Anima units.

Sheet Count
A1: Table 1
A2: Rarity | B2: Expected | C2: Percentage of Pool | D2: Notes | E2: Actual
A3: Common | B3: 52 | C3: 0.347 | D3: Filler / staple cards | E3: =_xlfn.COUNTIFS('Unit'!$J$3:$J$599,"Yes",'Unit'!$G$3:$G$599,1)+_xlfn.COUNTIFS('Trap'!$J$3:$J$544,"Yes",'Trap'!$G$3:$G$544,1)+_xlfn.COUNTIFS('Tech'!$J$3:$J$545,"Yes",'Tech'!$G$3:$G$545,1) -> 131
A4: Uncommon | B4: 48 | C4: 0.337 | D4: - | E4: =_xlfn.COUNTIFS('Unit'!$J$3:$J$599,"Yes",'Unit'!$G$3:$G$599,2)+_xlfn.COUNTIFS('Trap'!$J$3:$J$544,"Yes",'Trap'!$G$3:$G$544,2)+_xlfn.COUNTIFS('Tech'!$J$3:$J$545,"Yes",'Tech'!$G$3:$G$545,2) -> 118
A5: Rare | B5: 27 | C5: 0.167 | D5: - | E5: =_xlfn.COUNTIFS('Unit'!$J$3:$J$599,"Yes",'Unit'!$G$3:$G$599,3)+_xlfn.COUNTIFS('Trap'!$J$3:$J$544,"Yes",'Trap'!$G$3:$G$544,3)+_xlfn.COUNTIFS('Tech'!$J$3:$J$545,"Yes",'Tech'!$G$3:$G$545,3) -> 110
A6: Legendary | B6: 16 | C6: 0.1 | D6: Strong but not broken | E6: =_xlfn.COUNTIFS('Unit'!$J$3:$J$599,"Yes",'Unit'!$G$3:$G$599,4)+_xlfn.COUNTIFS('Trap'!$J$3:$J$544,"Yes",'Trap'!$G$3:$G$544,4)+_xlfn.COUNTIFS('Tech'!$J$3:$J$545,"Yes",'Tech'!$G$3:$G$545,4) -> 72
A7: Exotic | B7: 9 | C7: 0.053 | D7: Very desirable | E7: =_xlfn.COUNTIFS('Unit'!$J$3:$J$599,"Yes",'Unit'!$G$3:$G$599,5)+_xlfn.COUNTIFS('Trap'!$J$3:$J$544,"Yes",'Trap'!$G$3:$G$544,5)+_xlfn.COUNTIFS('Tech'!$J$3:$J$545,"Yes",'Tech'!$G$3:$G$545,5) -> 57
A11: Rarity | B11: Expected | E11: Actual
A12: Blightsilver | B12: 60 | E12: =_xlfn.COUNTIFS('Unit'!$N$3:$N$599,"Yes")+_xlfn.COUNTIFS('Trap'!$N$3:$N$544,"Yes")+_xlfn.COUNTIFS('Tech'!$N$3:$N$545,"Yes") -> 61
A13: Unseen Presence | B13: 60 | E13: =_xlfn.COUNTIFS('Unit'!$O$3:$O$599,"Yes")+_xlfn.COUNTIFS('Trap'!$O$3:$O$544,"Yes")+_xlfn.COUNTIFS('Tech'!$O$3:$O$545,"Yes") -> 60
A14: Wind of Dominance | B14: 60 | E14: =_xlfn.COUNTIFS('Unit'!$P$3:$P$599,"Yes")+_xlfn.COUNTIFS('Trap'!$P$3:$P$544,"Yes")+_xlfn.COUNTIFS('Tech'!$P$3:$P$545,"Yes") -> 60

Sheet Rule
A1: Table 1
B2: Old | C2: New
A3: 1 | B3: Foe | C3: foe
A4: 2 | B4: Battle calculation | C4: Reckoning
A5: 3 | B5: Cannot attack | C5: wait
A6: 4 | B6: ATK&DEF | C6: ATK&DEF
A7: 5 | B7: If head | C7: Head:
A8: 6 | B8: If tail | C8: Tail:
A9: 7 | B9: Square, grid | C9: cell
A10: 8 | B10: exposed | C10: Exposed
